[
    {
        "todo": null,
        "sentence_no": null,
        "begin": "255",
        "end": "266",
        "highlightText": "is designed",
        "replacements": [],
        "impact": "advanced",
        "categoryHuman": "Passive voice misuse",
        "id": 33,
        "starting_sentence": "# Prometheus  ## Int",
        "cell_number": 1
    },
    {
        "todo": "correct article usage",
        "sentence_no": "0",
        "begin": "2169",
        "end": "2173",
        "highlightText": "the network",
        "replacements": [
            ""
        ],
        "impact": "critical",
        "categoryHuman": "Determiner use (a/an/the/this, etc.)",
        "id": 34,
        "starting_sentence": "# Prometheus  ## Int",
        "cell_number": 1
    },
    {
        "todo": null,
        "sentence_no": null,
        "begin": "612",
        "end": "622",
        "highlightText": "is written",
        "replacements": [],
        "impact": "advanced",
        "categoryHuman": "Passive voice misuse",
        "id": 37,
        "starting_sentence": "# Prometheus  ## Int",
        "cell_number": 1
    },
    {
        "todo": "change the spelling",
        "sentence_no": "0",
        "begin": "626",
        "end": "632",
        "highlightText": "golang",
        "replacements": [],
        "impact": "critical",
        "categoryHuman": "Unknown words",
        "id": 36,
        "starting_sentence": "# Prometheus  ## Int",
        "cell_number": 1
    },
    {
        "todo": "change the capitalization",
        "sentence_no": "0",
        "begin": "626",
        "end": "632",
        "highlightText": "golang",
        "replacements": [
            "Golang"
        ],
        "impact": "critical",
        "categoryHuman": "Misspelled words",
        "id": 35,
        "starting_sentence": "# Prometheus  ## Int",
        "cell_number": 1
    },
    {
        "todo": null,
        "sentence_no": null,
        "begin": "2514",
        "end": "2518",
        "highlightText": "This",
        "replacements": [],
        "impact": "advanced",
        "categoryHuman": "Intricate text",
        "id": 38,
        "starting_sentence": "# Prometheus  ## Int",
        "cell_number": 1
    },
    {
        "todo": null,
        "sentence_no": null,
        "begin": "2543",
        "end": "2554",
        "highlightText": "is designed",
        "replacements": [],
        "impact": "advanced",
        "categoryHuman": "Passive voice misuse",
        "id": 39,
        "starting_sentence": "# Prometheus  ## Int",
        "cell_number": 1
    },
    {
        "todo": null,
        "sentence_no": null,
        "begin": "372",
        "end": "384",
        "highlightText": "was recorded",
        "replacements": [],
        "impact": "advanced",
        "categoryHuman": "Passive voice misuse",
        "id": 41,
        "starting_sentence": "# Prometheus  ## Int",
        "cell_number": 1
    },
    {
        "todo": null,
        "sentence_no": null,
        "begin": "385",
        "end": "386",
        "highlightText": "),",
        "replacements": [],
        "impact": "advanced",
        "categoryHuman": "Punctuation in compound/complex sentences",
        "id": 40,
        "starting_sentence": "# Prometheus  ## Int",
        "cell_number": 1
    },
    {
        "todo": null,
        "sentence_no": null,
        "begin": "787",
        "end": "802",
        "highlightText": "be employed to",
        "replacements": [],
        "impact": "advanced",
        "categoryHuman": "Wordy sentences",
        "id": 42,
        "starting_sentence": "# Prometheus  ## Int",
        "cell_number": 1
    },
    {
        "todo": null,
        "sentence_no": null,
        "begin": "1995",
        "end": "1995",
        "highlightText": "for",
        "replacements": [],
        "impact": "advanced",
        "categoryHuman": "Punctuation in compound/complex sentences",
        "id": 43,
        "starting_sentence": "# Prometheus  ## Int",
        "cell_number": 1
    },
    {
        "todo": "change the capitalization",
        "sentence_no": "0",
        "begin": "2090",
        "end": "2123",
        "highlightText": "slacks-outage-on-january-4th-2021",
        "replacements": [
            "slacks-outage-on-January-4th-2021"
        ],
        "impact": "critical",
        "categoryHuman": "Misspelled words",
        "id": 44,
        "starting_sentence": "# Prometheus  ## Int",
        "cell_number": 1
    },
    {
        "todo": null,
        "sentence_no": null,
        "begin": "2442",
        "end": "2461",
        "highlightText": "requests from users",
        "replacements": [],
        "impact": "advanced",
        "categoryHuman": "Wordy sentences",
        "id": 45,
        "starting_sentence": "# Prometheus  ## Int",
        "cell_number": 1
    },
    {
        "todo": null,
        "sentence_no": null,
        "begin": "187",
        "end": "197",
        "highlightText": "currently",
        "replacements": [],
        "impact": "advanced",
        "categoryHuman": "Wordy sentences",
        "id": 46,
        "starting_sentence": "# Prometheus  ## Int",
        "cell_number": 1
    },
    {
        "emotions": [],
        "action": "emotions",
        "starting_sentence": "# Prometheus  ## Int",
        "cell_number": 1
    },
    {
        "todo": null,
        "sentence_no": null,
        "begin": "31",
        "end": "41",
        "highlightText": "are stored",
        "replacements": [],
        "impact": "advanced",
        "categoryHuman": "Passive voice misuse",
        "id": 19,
        "starting_sentence": "## Data   All Promet",
        "cell_number": 1
    },
    {
        "todo": null,
        "sentence_no": null,
        "begin": "719",
        "end": "732",
        "highlightText": "being checked",
        "replacements": [],
        "impact": "advanced",
        "categoryHuman": "Passive voice misuse",
        "id": 20,
        "starting_sentence": "## Data   All Promet",
        "cell_number": 1
    },
    {
        "todo": null,
        "sentence_no": null,
        "begin": "617",
        "end": "630",
        "highlightText": "being checked",
        "replacements": [],
        "impact": "advanced",
        "categoryHuman": "Passive voice misuse",
        "id": 21,
        "starting_sentence": "## Data   All Promet",
        "cell_number": 1
    },
    {
        "emotions": [
            {
                "emoji": "\ud83d\udc54",
                "emojiId": "1f454",
                "name": "formal",
                "confidence": 0.9516601562
            },
            {
                "emoji": "\ud83e\udd13",
                "emojiId": "1f913",
                "name": "informative",
                "confidence": 0.9086914062
            },
            {
                "emoji": "\u261d\ufe0f",
                "emojiId": "261d",
                "name": "assertive",
                "confidence": 0.896484375
            }
        ],
        "action": "emotions",
        "starting_sentence": "## Data   All Promet",
        "cell_number": 1
    },
    {
        "todo": null,
        "sentence_no": null,
        "begin": "157",
        "end": "165",
        "highlightText": "are used",
        "replacements": [],
        "impact": "advanced",
        "categoryHuman": "Passive voice misuse",
        "id": 48,
        "starting_sentence": "## Metrics   Prometh",
        "cell_number": 1
    },
    {
        "todo": "change the capitalization",
        "sentence_no": "0",
        "begin": "219",
        "end": "225",
        "highlightText": "golang",
        "replacements": [
            "Golang"
        ],
        "impact": "critical",
        "categoryHuman": "Misspelled words",
        "id": 46,
        "starting_sentence": "## Metrics   Prometh",
        "cell_number": 1
    },
    {
        "todo": "correct word choice",
        "sentence_no": "0",
        "begin": "241",
        "end": "241",
        "highlightText": "ruby",
        "replacements": [
            "and "
        ],
        "impact": "critical",
        "categoryHuman": "Conjunction use",
        "id": 45,
        "starting_sentence": "## Metrics   Prometh",
        "cell_number": 1
    },
    {
        "todo": null,
        "sentence_no": null,
        "begin": "34",
        "end": "35",
        "highlightText": " 4 ",
        "replacements": [],
        "impact": "advanced",
        "categoryHuman": "Improper formatting",
        "id": 49,
        "starting_sentence": "## Metrics   Prometh",
        "cell_number": 1
    },
    {
        "todo": null,
        "sentence_no": null,
        "begin": "1596",
        "end": "1597",
        "highlightText": "endpoint,",
        "replacements": [],
        "impact": "advanced",
        "categoryHuman": "Punctuation in compound/complex sentences",
        "id": 50,
        "starting_sentence": "## Metrics   Prometh",
        "cell_number": 1
    },
    {
        "todo": null,
        "sentence_no": null,
        "begin": "1609",
        "end": "1628",
        "highlightText": "data can be scraped",
        "replacements": [],
        "impact": "advanced",
        "categoryHuman": "Passive voice misuse",
        "id": 51,
        "starting_sentence": "## Metrics   Prometh",
        "cell_number": 1
    },
    {
        "todo": null,
        "sentence_no": null,
        "begin": "1781",
        "end": "1807",
        "highlightText": "information regarding jobs",
        "replacements": [],
        "impact": "advanced",
        "categoryHuman": "Wordy sentences",
        "id": 52,
        "starting_sentence": "## Metrics   Prometh",
        "cell_number": 1
    },
    {
        "todo": null,
        "sentence_no": null,
        "begin": "307",
        "end": "331",
        "highlightText": "It can also be restarted",
        "replacements": [],
        "impact": "advanced",
        "categoryHuman": "Passive voice misuse",
        "id": 53,
        "starting_sentence": "## Metrics   Prometh",
        "cell_number": 1
    },
    {
        "todo": null,
        "sentence_no": null,
        "begin": "1420",
        "end": "1451",
        "highlightText": "Functions  Functions can be run",
        "replacements": [],
        "impact": "advanced",
        "categoryHuman": "Passive voice misuse",
        "id": 54,
        "starting_sentence": "## Metrics   Prometh",
        "cell_number": 1
    },
    {
        "todo": null,
        "sentence_no": null,
        "begin": "1463",
        "end": "1474",
        "highlightText": "for things",
        "replacements": [],
        "impact": "advanced",
        "categoryHuman": "Wordy sentences",
        "id": 55,
        "starting_sentence": "## Metrics   Prometh",
        "cell_number": 1
    },
    {
        "todo": "change the verb form",
        "sentence_no": "0",
        "begin": "1363",
        "end": "1363",
        "highlightText": "achieved",
        "replacements": [
            "be "
        ],
        "impact": "critical",
        "categoryHuman": "Modal verbs",
        "id": 56,
        "starting_sentence": "## Metrics   Prometh",
        "cell_number": 1
    },
    {
        "todo": "correct your spelling",
        "sentence_no": "0",
        "begin": "241",
        "end": "245",
        "highlightText": "ruby",
        "replacements": [
            "Ruby"
        ],
        "impact": "critical",
        "categoryHuman": "Confused words",
        "id": 47,
        "starting_sentence": "## Metrics   Prometh",
        "cell_number": 1
    },
    {
        "emotions": [
            {
                "emoji": "\ud83d\udc54",
                "emojiId": "1f454",
                "name": "formal",
                "confidence": 0.9990234375
            }
        ],
        "action": "emotions",
        "starting_sentence": "## Metrics   Prometh",
        "cell_number": 1
    },
    {
        "todo": null,
        "sentence_no": null,
        "begin": "815",
        "end": "825",
        "highlightText": "Thereafter",
        "replacements": [],
        "impact": "advanced",
        "categoryHuman": "Outdated language",
        "id": 25,
        "starting_sentence": "## First Contact  ##",
        "cell_number": 1
    },
    {
        "todo": null,
        "sentence_no": null,
        "begin": "887",
        "end": "887",
        "highlightText": "code",
        "replacements": [],
        "impact": "advanced",
        "categoryHuman": "Closing punctuation",
        "id": 24,
        "starting_sentence": "## First Contact  ##",
        "cell_number": 1
    },
    {
        "todo": null,
        "sentence_no": null,
        "begin": "648",
        "end": "652",
        "highlightText": "This",
        "replacements": [],
        "impact": "advanced",
        "categoryHuman": "Intricate text",
        "id": 26,
        "starting_sentence": "## First Contact  ##",
        "cell_number": 1
    },
    {
        "todo": null,
        "sentence_no": null,
        "begin": "430",
        "end": "431",
        "highlightText": "labelled,",
        "replacements": [],
        "impact": "advanced",
        "categoryHuman": "Punctuation in compound/complex sentences",
        "id": 27,
        "starting_sentence": "## First Contact  ##",
        "cell_number": 1
    },
    {
        "todo": null,
        "sentence_no": null,
        "begin": "1",
        "end": "60",
        "highlightText": "## First Contact  ### Installation   Prometheus was written",
        "replacements": [],
        "impact": "advanced",
        "categoryHuman": "Passive voice misuse",
        "id": 30,
        "starting_sentence": "## First Contact  ##",
        "cell_number": 1
    },
    {
        "todo": "change the spelling",
        "sentence_no": "0",
        "begin": "64",
        "end": "70",
        "highlightText": "golang",
        "replacements": [],
        "impact": "critical",
        "categoryHuman": "Unknown words",
        "id": 29,
        "starting_sentence": "## First Contact  ##",
        "cell_number": 1
    },
    {
        "todo": "change the capitalization",
        "sentence_no": "0",
        "begin": "64",
        "end": "70",
        "highlightText": "golang",
        "replacements": [
            "Golang"
        ],
        "impact": "critical",
        "categoryHuman": "Misspelled words",
        "id": 28,
        "starting_sentence": "## First Contact  ##",
        "cell_number": 1
    },
    {
        "todo": null,
        "sentence_no": null,
        "begin": "82",
        "end": "94",
        "highlightText": "is contained",
        "replacements": [],
        "impact": "advanced",
        "categoryHuman": "Passive voice misuse",
        "id": 31,
        "starting_sentence": "## First Contact  ##",
        "cell_number": 1
    },
    {
        "todo": "change the capitalization",
        "sentence_no": "0",
        "begin": "803",
        "end": "813",
        "highlightText": "prometheus",
        "replacements": [
            "Prometheus"
        ],
        "impact": "critical",
        "categoryHuman": "Misspelled words",
        "id": 32,
        "starting_sentence": "## First Contact  ##",
        "cell_number": 1
    },
    {
        "todo": "correct your spelling",
        "sentence_no": "0",
        "begin": "883",
        "end": "888",
        "highlightText": "code'",
        "replacements": [
            "code"
        ],
        "impact": "critical",
        "categoryHuman": "Confused words",
        "id": 22,
        "starting_sentence": "## First Contact  ##",
        "cell_number": 1
    },
    {
        "emotions": [
            {
                "emoji": "\ud83d\udc54",
                "emojiId": "1f454",
                "name": "formal",
                "confidence": 0.9990234375
            }
        ],
        "action": "emotions",
        "starting_sentence": "## First Contact  ##",
        "cell_number": 1
    },
    {
        "todo": "add a\u00a0space",
        "sentence_no": "0",
        "begin": "287",
        "end": "287",
        "highlightText": ".enable-lifecycle",
        "replacements": [
            " "
        ],
        "impact": "critical",
        "categoryHuman": "Improper formatting",
        "id": 13,
        "starting_sentence": "Subsequently, we can",
        "cell_number": 1
    },
    {
        "todo": null,
        "sentence_no": null,
        "begin": "76",
        "end": "83",
        "highlightText": "have to",
        "replacements": [],
        "impact": "advanced",
        "categoryHuman": "Wordy sentences",
        "id": 14,
        "starting_sentence": "Subsequently, we can",
        "cell_number": 1
    },
    {
        "emotions": [
            {
                "emoji": "\ud83d\udc54",
                "emojiId": "1f454",
                "name": "formal",
                "confidence": 0.9853515625
            },
            {
                "emoji": "\ud83e\udd13",
                "emojiId": "1f913",
                "name": "informative",
                "confidence": 0.9819335938
            }
        ],
        "action": "emotions",
        "starting_sentence": "Subsequently, we can",
        "cell_number": 1
    },
    {
        "todo": null,
        "sentence_no": null,
        "begin": "841",
        "end": "851",
        "highlightText": "are logged",
        "replacements": [],
        "impact": "advanced",
        "categoryHuman": "Passive voice misuse",
        "id": 21,
        "starting_sentence": "### Docker options -",
        "cell_number": 1
    },
    {
        "todo": null,
        "sentence_no": null,
        "begin": "62",
        "end": "66",
        "highlightText": "This",
        "replacements": [],
        "impact": "advanced",
        "categoryHuman": "Intricate text",
        "id": 22,
        "starting_sentence": "### Docker options -",
        "cell_number": 1
    },
    {
        "todo": null,
        "sentence_no": null,
        "begin": "110",
        "end": "118",
        "highlightText": "thereby",
        "replacements": [],
        "impact": "advanced",
        "categoryHuman": "Wordy sentences",
        "id": 23,
        "starting_sentence": "### Docker options -",
        "cell_number": 1
    },
    {
        "todo": "add a\u00a0space",
        "sentence_no": "0",
        "begin": "154",
        "end": "154",
        "highlightText": ".file",
        "replacements": [
            " "
        ],
        "impact": "critical",
        "categoryHuman": "Improper formatting",
        "id": 24,
        "starting_sentence": "### Docker options -",
        "cell_number": 1
    },
    {
        "todo": null,
        "sentence_no": null,
        "begin": "174",
        "end": "211",
        "highlightText": "the prometheus.yml file will be found",
        "replacements": [],
        "impact": "advanced",
        "categoryHuman": "Passive voice misuse",
        "id": 25,
        "starting_sentence": "### Docker options -",
        "cell_number": 1
    },
    {
        "todo": null,
        "sentence_no": null,
        "begin": "910",
        "end": "925",
        "highlightText": "so that you can",
        "replacements": [],
        "impact": "advanced",
        "categoryHuman": "Wordy sentences",
        "id": 26,
        "starting_sentence": "### Docker options -",
        "cell_number": 1
    },
    {
        "todo": "change the capitalization",
        "sentence_no": "0",
        "begin": "1326",
        "end": "1336",
        "highlightText": "prometheus",
        "replacements": [
            "Prometheus"
        ],
        "impact": "critical",
        "categoryHuman": "Misspelled words",
        "id": 27,
        "starting_sentence": "### Docker options -",
        "cell_number": 1
    },
    {
        "todo": null,
        "sentence_no": null,
        "begin": "1181",
        "end": "1194",
        "highlightText": "be configured",
        "replacements": [],
        "impact": "advanced",
        "categoryHuman": "Passive voice misuse",
        "id": 28,
        "starting_sentence": "### Docker options -",
        "cell_number": 1
    },
    {
        "todo": null,
        "sentence_no": null,
        "begin": "458",
        "end": "610",
        "highlightText": "- -network=host maps the ports on the local machine to the ports inside the Docker container for when the localhost host is specified in prometheus.yml.",
        "replacements": [],
        "impact": "advanced",
        "categoryHuman": "Intricate text",
        "id": 30,
        "starting_sentence": "### Docker options -",
        "cell_number": 1
    },
    {
        "todo": "change preposition",
        "sentence_no": "0",
        "begin": "551",
        "end": "555",
        "highlightText": "for",
        "replacements": [
            ""
        ],
        "impact": "critical",
        "categoryHuman": "Wrong or missing prepositions",
        "id": 29,
        "starting_sentence": "### Docker options -",
        "cell_number": 1
    },
    {
        "todo": null,
        "sentence_no": null,
        "begin": "579",
        "end": "591",
        "highlightText": "is specified",
        "replacements": [],
        "impact": "advanced",
        "categoryHuman": "Passive voice misuse",
        "id": 31,
        "starting_sentence": "### Docker options -",
        "cell_number": 1
    },
    {
        "todo": "change the capitalization",
        "sentence_no": "0",
        "begin": "366",
        "end": "376",
        "highlightText": "prometheus",
        "replacements": [
            "Prometheus"
        ],
        "impact": "critical",
        "categoryHuman": "Misspelled words",
        "id": 32,
        "starting_sentence": "### Docker options -",
        "cell_number": 1
    },
    {
        "todo": "change the wording",
        "sentence_no": "0",
        "begin": "422",
        "end": "433",
        "highlightText": "in order to",
        "replacements": [
            "to"
        ],
        "impact": "advanced",
        "categoryHuman": "Wordy sentences",
        "id": 33,
        "starting_sentence": "### Docker options -",
        "cell_number": 1
    },
    {
        "emotions": [
            {
                "emoji": "\ud83d\udc54",
                "emojiId": "1f454",
                "name": "formal",
                "confidence": 0.9970703125
            },
            {
                "emoji": "\ud83e\udd13",
                "emojiId": "1f913",
                "name": "informative",
                "confidence": 0.9780273438000004
            }
        ],
        "action": "emotions",
        "starting_sentence": "### Docker options -",
        "cell_number": 1
    },
    {
        "todo": null,
        "sentence_no": null,
        "begin": "345",
        "end": "432",
        "highlightText": "A test list of all metrics currently being logged by the Prometheus server can be found",
        "replacements": [],
        "impact": "advanced",
        "categoryHuman": "Passive voice misuse",
        "id": 7,
        "starting_sentence": "The results of the q",
        "cell_number": 1
    },
    {
        "todo": null,
        "sentence_no": null,
        "begin": "382",
        "end": "388",
        "highlightText": "being",
        "replacements": [],
        "impact": "advanced",
        "categoryHuman": "Wordy sentences",
        "id": 8,
        "starting_sentence": "The results of the q",
        "cell_number": 1
    },
    {
        "emotions": [
            {
                "emoji": "\ud83e\udd1d",
                "emojiId": "1f91d",
                "name": "confident",
                "confidence": 0.9526367188
            },
            {
                "emoji": "\u2696\ufe0f",
                "emojiId": "2696",
                "name": "objective",
                "confidence": 0.8159179688
            }
        ],
        "action": "emotions",
        "starting_sentence": "The results of the q",
        "cell_number": 1
    },
    {
        "todo": null,
        "sentence_no": null,
        "begin": "424",
        "end": "456",
        "highlightText": "obtain a better understanding of",
        "replacements": [],
        "impact": "advanced",
        "categoryHuman": "Wordy sentences",
        "id": 7,
        "starting_sentence": "## Prometheus Config",
        "cell_number": 1
    },
    {
        "todo": null,
        "sentence_no": null,
        "begin": "167",
        "end": "174",
        "highlightText": "is used",
        "replacements": [],
        "impact": "advanced",
        "categoryHuman": "Passive voice misuse",
        "id": 8,
        "starting_sentence": "## Prometheus Config",
        "cell_number": 1
    },
    {
        "todo": null,
        "sentence_no": null,
        "begin": "167",
        "end": "184",
        "highlightText": "is used to define",
        "replacements": [],
        "impact": "advanced",
        "categoryHuman": "Wordy sentences",
        "id": 9,
        "starting_sentence": "## Prometheus Config",
        "cell_number": 1
    },
    {
        "emotions": [
            {
                "emoji": "\ud83e\udd13",
                "emojiId": "1f913",
                "name": "informative",
                "confidence": 1.0
            }
        ],
        "action": "emotions",
        "starting_sentence": "## Prometheus Config",
        "cell_number": 1
    },
    {
        "todo": null,
        "sentence_no": null,
        "begin": "770",
        "end": "771",
        "highlightText": "parameters,",
        "replacements": [],
        "impact": "advanced",
        "categoryHuman": "Punctuation in compound/complex sentences",
        "id": 10,
        "starting_sentence": " Prometheus provides",
        "cell_number": 1
    },
    {
        "emotions": [
            {
                "emoji": "\ud83d\udc54",
                "emojiId": "1f454",
                "name": "formal",
                "confidence": 1.0
            }
        ],
        "action": "emotions",
        "starting_sentence": " Prometheus provides",
        "cell_number": 1
    },
    {
        "todo": null,
        "sentence_no": null,
        "begin": "323",
        "end": "323",
        "highlightText": "follows",
        "replacements": [],
        "impact": "advanced",
        "categoryHuman": "Closing punctuation",
        "id": 12,
        "starting_sentence": "By adding the --web.",
        "cell_number": 1
    },
    {
        "todo": "correct your spelling",
        "sentence_no": "0",
        "begin": "316",
        "end": "324",
        "highlightText": "follows'",
        "replacements": [
            "follows"
        ],
        "impact": "critical",
        "categoryHuman": "Confused words",
        "id": 11,
        "starting_sentence": "By adding the --web.",
        "cell_number": 1
    },
    {
        "emotions": [
            {
                "emoji": "\u261d\ufe0f",
                "emojiId": "261d",
                "name": "assertive",
                "confidence": 0.9951171875
            },
            {
                "emoji": "\ud83d\udc54",
                "emojiId": "1f454",
                "name": "formal",
                "confidence": 0.5791015625
            }
        ],
        "action": "emotions",
        "starting_sentence": "By adding the --web.",
        "cell_number": 1
    },
    {
        "todo": null,
        "sentence_no": null,
        "begin": "202",
        "end": "202",
        "highlightText": ")",
        "replacements": [],
        "impact": "advanced",
        "categoryHuman": "Closing punctuation",
        "id": 7,
        "starting_sentence": "Now, we can run the ",
        "cell_number": 1
    },
    {
        "todo": null,
        "sentence_no": null,
        "begin": "88",
        "end": "98",
        "highlightText": "is running",
        "replacements": [],
        "impact": "advanced",
        "categoryHuman": "Wordy sentences",
        "id": 8,
        "starting_sentence": "Now, we can run the ",
        "cell_number": 1
    },
    {
        "emotions": [
            {
                "emoji": "\ud83e\udd13",
                "emojiId": "1f913",
                "name": "informative",
                "confidence": 1.0
            }
        ],
        "action": "emotions",
        "starting_sentence": "Now, we can run the ",
        "cell_number": 1
    },
    {
        "todo": null,
        "sentence_no": null,
        "begin": "58",
        "end": "78",
        "highlightText": "It should be updated",
        "replacements": [],
        "impact": "advanced",
        "categoryHuman": "Passive voice misuse",
        "id": 7,
        "starting_sentence": "Now, go to localhost",
        "cell_number": 1
    },
    {
        "emotions": [],
        "action": "emotions",
        "starting_sentence": "Now, go to localhost",
        "cell_number": 1
    },
    {
        "todo": "change the capitalization",
        "sentence_no": "0",
        "begin": "1378",
        "end": "1388",
        "highlightText": "prometheus",
        "replacements": [
            "Prometheus"
        ],
        "impact": "critical",
        "categoryHuman": "Misspelled words",
        "id": 16,
        "starting_sentence": "### [scrape_configs]",
        "cell_number": 1
    },
    {
        "todo": null,
        "sentence_no": null,
        "begin": "394",
        "end": "416",
        "highlightText": "Targets can be defined",
        "replacements": [],
        "impact": "advanced",
        "categoryHuman": "Passive voice misuse",
        "id": 17,
        "starting_sentence": "### [scrape_configs]",
        "cell_number": 1
    },
    {
        "todo": "change the capitalization",
        "sentence_no": "0",
        "begin": "48",
        "end": "58",
        "highlightText": "prometheus",
        "replacements": [
            "Prometheus"
        ],
        "impact": "critical",
        "categoryHuman": "Misspelled words",
        "id": 18,
        "starting_sentence": "### [scrape_configs]",
        "cell_number": 1
    },
    {
        "todo": null,
        "sentence_no": null,
        "begin": "165",
        "end": "175",
        "highlightText": "be scraped",
        "replacements": [],
        "impact": "advanced",
        "categoryHuman": "Passive voice misuse",
        "id": 19,
        "starting_sentence": "### [scrape_configs]",
        "cell_number": 1
    },
    {
        "todo": null,
        "sentence_no": null,
        "begin": "719",
        "end": "751",
        "highlightText": "docker containers may be started",
        "replacements": [],
        "impact": "advanced",
        "categoryHuman": "Passive voice misuse",
        "id": 20,
        "starting_sentence": "### [scrape_configs]",
        "cell_number": 1
    },
    {
        "todo": null,
        "sentence_no": null,
        "begin": "890",
        "end": "905",
        "highlightText": "will be able to",
        "replacements": [],
        "impact": "advanced",
        "categoryHuman": "Wordy sentences",
        "id": 21,
        "starting_sentence": "### [scrape_configs]",
        "cell_number": 1
    },
    {
        "todo": "change the capitalization",
        "sentence_no": "0",
        "begin": "1140",
        "end": "1150",
        "highlightText": "prometheus",
        "replacements": [
            "Prometheus"
        ],
        "impact": "critical",
        "categoryHuman": "Misspelled words",
        "id": 22,
        "starting_sentence": "### [scrape_configs]",
        "cell_number": 1
    },
    {
        "todo": "change the capitalization",
        "sentence_no": "0",
        "begin": "2010",
        "end": "2020",
        "highlightText": "prometheus",
        "replacements": [
            "Prometheus"
        ],
        "impact": "critical",
        "categoryHuman": "Misspelled words",
        "id": 23,
        "starting_sentence": "### [scrape_configs]",
        "cell_number": 1
    },
    {
        "emotions": [
            {
                "emoji": "\ud83d\udc54",
                "emojiId": "1f454",
                "name": "formal",
                "confidence": 0.994140625
            }
        ],
        "action": "emotions",
        "starting_sentence": "### [scrape_configs]",
        "cell_number": 1
    },
    {
        "todo": null,
        "sentence_no": null,
        "begin": "156",
        "end": "156",
        "highlightText": "options",
        "replacements": [],
        "impact": "advanced",
        "categoryHuman": "Closing punctuation",
        "id": 8,
        "starting_sentence": "### Command line   I",
        "cell_number": 1
    },
    {
        "todo": "correct your spelling",
        "sentence_no": "0",
        "begin": "149",
        "end": "157",
        "highlightText": "options'",
        "replacements": [
            "options"
        ],
        "impact": "critical",
        "categoryHuman": "Confused words",
        "id": 7,
        "starting_sentence": "### Command line   I",
        "cell_number": 1
    },
    {
        "emotions": [
            {
                "emoji": "\ud83e\udd13",
                "emojiId": "1f913",
                "name": "informative",
                "confidence": 0.9819335938
            },
            {
                "emoji": "\ud83e\udd1d",
                "emojiId": "1f91d",
                "name": "confident",
                "confidence": 0.9741210938
            }
        ],
        "action": "emotions",
        "starting_sentence": "### Command line   I",
        "cell_number": 1
    },
    {
        "todo": "change the spelling",
        "sentence_no": "0",
        "begin": "427",
        "end": "431",
        "highlightText": "tsdb",
        "replacements": [],
        "impact": "critical",
        "categoryHuman": "Unknown words",
        "id": 16,
        "starting_sentence": "The most notable opt",
        "cell_number": 1
    },
    {
        "todo": null,
        "sentence_no": null,
        "begin": "359",
        "end": "362",
        "highlightText": "...",
        "replacements": [],
        "impact": "advanced",
        "categoryHuman": "Misuse of semicolons, quotation marks, etc.",
        "id": 17,
        "starting_sentence": "The most notable opt",
        "cell_number": 1
    },
    {
        "todo": null,
        "sentence_no": null,
        "begin": "830",
        "end": "834",
        "highlightText": "This",
        "replacements": [],
        "impact": "advanced",
        "categoryHuman": "Intricate text",
        "id": 19,
        "starting_sentence": "The most notable opt",
        "cell_number": 1
    },
    {
        "todo": "correct your spelling",
        "sentence_no": "0",
        "begin": "922",
        "end": "928",
        "highlightText": "golang",
        "replacements": [
            "going"
        ],
        "impact": "critical",
        "categoryHuman": "Misspelled words",
        "id": 18,
        "starting_sentence": "The most notable opt",
        "cell_number": 1
    },
    {
        "todo": null,
        "sentence_no": null,
        "begin": "657",
        "end": "674",
        "highlightText": "of the following",
        "replacements": [],
        "impact": "advanced",
        "categoryHuman": "Wordy sentences",
        "id": 20,
        "starting_sentence": "The most notable opt",
        "cell_number": 1
    },
    {
        "todo": "correct article usage",
        "sentence_no": "0",
        "begin": "805",
        "end": "805",
        "highlightText": "option",
        "replacements": [
            "the "
        ],
        "impact": "critical",
        "categoryHuman": "Determiner use (a/an/the/this, etc.)",
        "id": 21,
        "starting_sentence": "The most notable opt",
        "cell_number": 1
    },
    {
        "todo": null,
        "sentence_no": null,
        "begin": "823",
        "end": "827",
        "highlightText": "one",
        "replacements": [],
        "impact": "advanced",
        "categoryHuman": "Wordy sentences",
        "id": 22,
        "starting_sentence": "The most notable opt",
        "cell_number": 1
    },
    {
        "emotions": [
            {
                "emoji": "\ud83e\udd13",
                "emojiId": "1f913",
                "name": "informative",
                "confidence": 0.99609375
            }
        ],
        "action": "emotions",
        "starting_sentence": "The most notable opt",
        "cell_number": 1
    },
    {
        "todo": null,
        "sentence_no": null,
        "begin": "296",
        "end": "640",
        "highlightText": "The full list of the most common ones can be found [here](https//prometheus.io/docs/instrumenting/exporters/), and a complete list of all exporters on GitHub can be found [here](https//github.com/prometheus/prometheus/wiki/Default-port-allocations) - **official** best practices, and verified by Prometheus (always pick them whenever possible).",
        "replacements": [],
        "impact": "advanced",
        "categoryHuman": "Hard-to-read text",
        "id": 23,
        "starting_sentence": "## Exporters   Expor",
        "cell_number": 1
    },
    {
        "todo": "change the spelling",
        "sentence_no": "0",
        "begin": "492",
        "end": "502",
        "highlightText": "prometheus",
        "replacements": [],
        "impact": "critical",
        "categoryHuman": "Unknown words",
        "id": 22,
        "starting_sentence": "## Exporters   Expor",
        "cell_number": 1
    },
    {
        "todo": "change the capitalization",
        "sentence_no": "0",
        "begin": "503",
        "end": "513",
        "highlightText": "prometheus",
        "replacements": [
            "Prometheus"
        ],
        "impact": "critical",
        "categoryHuman": "Misspelled words",
        "id": 21,
        "starting_sentence": "## Exporters   Expor",
        "cell_number": 1
    },
    {
        "todo": null,
        "sentence_no": null,
        "begin": "783",
        "end": "793",
        "highlightText": "either of",
        "replacements": [],
        "impact": "advanced",
        "categoryHuman": "Wordy sentences",
        "id": 24,
        "starting_sentence": "## Exporters   Expor",
        "cell_number": 1
    },
    {
        "todo": "change the spelling",
        "sentence_no": "0",
        "begin": "1249",
        "end": "1259",
        "highlightText": "prometheus",
        "replacements": [],
        "impact": "critical",
        "categoryHuman": "Unknown words",
        "id": 25,
        "starting_sentence": "## Exporters   Expor",
        "cell_number": 1
    },
    {
        "todo": null,
        "sentence_no": null,
        "begin": "158",
        "end": "211",
        "highlightText": "For example, an exporter for tracking GitHub metrics.",
        "replacements": [],
        "impact": "advanced",
        "categoryHuman": "Incomplete sentences",
        "id": 27,
        "starting_sentence": "## Exporters   Expor",
        "cell_number": 1
    },
    {
        "todo": null,
        "sentence_no": null,
        "begin": "300",
        "end": "304",
        "highlightText": "full",
        "replacements": [],
        "impact": "advanced",
        "categoryHuman": "Word choice",
        "id": 26,
        "starting_sentence": "## Exporters   Expor",
        "cell_number": 1
    },
    {
        "emotions": [
            {
                "emoji": "\ud83e\udd13",
                "emojiId": "1f913",
                "name": "informative",
                "confidence": 1.0
            }
        ],
        "action": "emotions",
        "starting_sentence": "## Exporters   Expor",
        "cell_number": 1
    },
    {
        "todo": null,
        "sentence_no": null,
        "begin": "63",
        "end": "70",
        "highlightText": "single",
        "replacements": [],
        "impact": "advanced",
        "categoryHuman": "Wordy sentences",
        "id": 12,
        "starting_sentence": "### Setting up Node ",
        "cell_number": 1
    },
    {
        "todo": null,
        "sentence_no": null,
        "begin": "89",
        "end": "106",
        "highlightText": "can be downloaded",
        "replacements": [],
        "impact": "advanced",
        "categoryHuman": "Passive voice misuse",
        "id": 11,
        "starting_sentence": "### Setting up Node ",
        "cell_number": 1
    },
    {
        "todo": null,
        "sentence_no": null,
        "begin": "282",
        "end": "282",
        "highlightText": "may",
        "replacements": [],
        "impact": "advanced",
        "categoryHuman": "Incomplete sentences",
        "id": 13,
        "starting_sentence": "### Setting up Node ",
        "cell_number": 1
    },
    {
        "todo": null,
        "sentence_no": null,
        "begin": "197",
        "end": "198",
        "highlightText": "exporter,",
        "replacements": [],
        "impact": "advanced",
        "categoryHuman": "Punctuation in compound/complex sentences",
        "id": 14,
        "starting_sentence": "### Setting up Node ",
        "cell_number": 1
    },
    {
        "todo": "change the spelling",
        "sentence_no": "0",
        "begin": "219",
        "end": "221",
        "highlightText": "gz",
        "replacements": [],
        "impact": "critical",
        "categoryHuman": "Unknown words",
        "id": 15,
        "starting_sentence": "### Setting up Node ",
        "cell_number": 1
    },
    {
        "emotions": [
            {
                "emoji": "\ud83e\udd13",
                "emojiId": "1f913",
                "name": "informative",
                "confidence": 0.9990234375
            }
        ],
        "action": "emotions",
        "starting_sentence": "### Setting up Node ",
        "cell_number": 1
    },
    {
        "todo": "change the spelling",
        "sentence_no": "0",
        "begin": "137",
        "end": "141",
        "highlightText": "xvzf",
        "replacements": [],
        "impact": "critical",
        "categoryHuman": "Unknown words",
        "id": 4,
        "starting_sentence": "Note Add the followi",
        "cell_number": 1
    },
    {
        "todo": null,
        "sentence_no": null,
        "begin": "141",
        "end": "143",
        "highlightText": "After",
        "replacements": [],
        "impact": "advanced",
        "categoryHuman": "Punctuation in compound/complex sentences",
        "id": 6,
        "starting_sentence": "Note Add the followi",
        "cell_number": 1
    },
    {
        "todo": null,
        "sentence_no": null,
        "begin": "287",
        "end": "287",
        "highlightText": "modified=23213234453",
        "replacements": [],
        "impact": "advanced",
        "categoryHuman": "Closing punctuation",
        "id": 5,
        "starting_sentence": "Note Add the followi",
        "cell_number": 1
    },
    {
        "emotions": [
            {
                "emoji": "\ud83e\udd13",
                "emojiId": "1f913",
                "name": "informative",
                "confidence": 1.0
            }
        ],
        "action": "emotions",
        "starting_sentence": "Note Add the followi",
        "cell_number": 1
    },
    {
        "todo": "change the capitalization",
        "sentence_no": "0",
        "begin": "314",
        "end": "319",
        "highlightText": "linux",
        "replacements": [
            "Linux"
        ],
        "impact": "critical",
        "categoryHuman": "Misspelled words",
        "id": 9,
        "starting_sentence": "### Configuring Prom",
        "cell_number": 1
    },
    {
        "todo": "change the capitalization",
        "sentence_no": "0",
        "begin": "314",
        "end": "319",
        "highlightText": "linux",
        "replacements": [
            "Linux"
        ],
        "impact": "critical",
        "categoryHuman": "Misspelled words",
        "id": 11,
        "starting_sentence": "### Configuring Prom",
        "cell_number": 1
    },
    {
        "todo": null,
        "sentence_no": null,
        "begin": "233",
        "end": "249",
        "highlightText": "which will allow",
        "replacements": [],
        "impact": "advanced",
        "categoryHuman": "Wordy sentences",
        "id": 12,
        "starting_sentence": "### Configuring Prom",
        "cell_number": 1
    },
    {
        "todo": "correct your spelling",
        "sentence_no": "0",
        "begin": "324",
        "end": "332",
        "highlightText": "systems'",
        "replacements": [
            "systems"
        ],
        "impact": "critical",
        "categoryHuman": "Confused words",
        "id": 8,
        "starting_sentence": "### Configuring Prom",
        "cell_number": 1
    },
    {
        "emotions": [
            {
                "emoji": "\u261d\ufe0f",
                "emojiId": "261d",
                "name": "assertive",
                "confidence": 0.9970703125
            },
            {
                "emoji": "\ud83d\udc54",
                "emojiId": "1f454",
                "name": "formal",
                "confidence": 0.88671875
            }
        ],
        "action": "emotions",
        "starting_sentence": "### Configuring Prom",
        "cell_number": 1
    },
    {
        "todo": null,
        "sentence_no": null,
        "begin": "75",
        "end": "75",
        "highlightText": "is",
        "replacements": [],
        "impact": "advanced",
        "categoryHuman": "Closing punctuation",
        "id": 4,
        "starting_sentence": "As can be observed, ",
        "cell_number": 1
    },
    {
        "emotions": [],
        "action": "emotions",
        "starting_sentence": "As can be observed, ",
        "cell_number": 1
    },
    {
        "todo": null,
        "sentence_no": null,
        "begin": "800",
        "end": "806",
        "highlightText": "it is",
        "replacements": [],
        "impact": "advanced",
        "categoryHuman": "Wordy sentences",
        "id": 21,
        "starting_sentence": "Now, we need to pass",
        "cell_number": 1
    },
    {
        "todo": null,
        "sentence_no": null,
        "begin": "982",
        "end": "1003",
        "highlightText": "At this point, we can",
        "replacements": [],
        "impact": "advanced",
        "categoryHuman": "Wordy sentences",
        "id": 22,
        "starting_sentence": "Now, we need to pass",
        "cell_number": 1
    },
    {
        "todo": null,
        "sentence_no": null,
        "begin": "80",
        "end": "92",
        "highlightText": "is contained",
        "replacements": [],
        "impact": "advanced",
        "categoryHuman": "Passive voice misuse",
        "id": 23,
        "starting_sentence": "Now, we need to pass",
        "cell_number": 1
    },
    {
        "todo": null,
        "sentence_no": null,
        "begin": "83",
        "end": "93",
        "highlightText": "contained",
        "replacements": [],
        "impact": "advanced",
        "categoryHuman": "Wordy sentences",
        "id": 24,
        "starting_sentence": "Now, we need to pass",
        "cell_number": 1
    },
    {
        "todo": null,
        "sentence_no": null,
        "begin": "184",
        "end": "185",
        "highlightText": "first,",
        "replacements": [],
        "impact": "advanced",
        "categoryHuman": "Punctuation in compound/complex sentences",
        "id": 27,
        "starting_sentence": "Now, we need to pass",
        "cell_number": 1
    },
    {
        "todo": "correct pronoun usage",
        "sentence_no": "0",
        "begin": "186",
        "end": "190",
        "highlightText": "one",
        "replacements": [
            ""
        ],
        "impact": "critical",
        "categoryHuman": "Pronoun use",
        "id": 25,
        "starting_sentence": "Now, we need to pass",
        "cell_number": 1
    },
    {
        "todo": null,
        "sentence_no": null,
        "begin": "186",
        "end": "202",
        "highlightText": "one which allows",
        "replacements": [],
        "impact": "advanced",
        "categoryHuman": "Wordy sentences",
        "id": 28,
        "starting_sentence": "Now, we need to pass",
        "cell_number": 1
    },
    {
        "todo": null,
        "sentence_no": null,
        "begin": "189",
        "end": "189",
        "highlightText": "which",
        "replacements": [],
        "impact": "advanced",
        "categoryHuman": "Punctuation in compound/complex sentences",
        "id": 26,
        "starting_sentence": "Now, we need to pass",
        "cell_number": 1
    },
    {
        "todo": "change the capitalization",
        "sentence_no": "0",
        "begin": "946",
        "end": "956",
        "highlightText": "prometheus",
        "replacements": [
            "Prometheus"
        ],
        "impact": "critical",
        "categoryHuman": "Misspelled words",
        "id": 29,
        "starting_sentence": "Now, we need to pass",
        "cell_number": 1
    },
    {
        "todo": "correct article usage",
        "sentence_no": "0",
        "begin": "515",
        "end": "515",
        "highlightText": "autoreload",
        "replacements": [
            "an "
        ],
        "impact": "critical",
        "categoryHuman": "Determiner use (a/an/the/this, etc.)",
        "id": 30,
        "starting_sentence": "Now, we need to pass",
        "cell_number": 1
    },
    {
        "todo": "correct your spelling",
        "sentence_no": "0",
        "begin": "515",
        "end": "525",
        "highlightText": "autoreload",
        "replacements": [
            "autoload",
            "auto reload",
            "auto-reload"
        ],
        "impact": "critical",
        "categoryHuman": "Misspelled words",
        "id": 31,
        "starting_sentence": "Now, we need to pass",
        "cell_number": 1
    },
    {
        "emotions": [
            {
                "emoji": "\ud83e\udd13",
                "emojiId": "1f913",
                "name": "informative",
                "confidence": 1.0
            }
        ],
        "action": "emotions",
        "starting_sentence": "Now, we need to pass",
        "cell_number": 1
    },
    {
        "todo": "add an\u00a0article",
        "sentence_no": "0",
        "begin": "922",
        "end": "922",
        "highlightText": "node",
        "replacements": [
            "the "
        ],
        "impact": "critical",
        "categoryHuman": "Determiner use (a/an/the/this, etc.)",
        "id": 16,
        "starting_sentence": "Go to [localhost9090",
        "cell_number": 1
    },
    {
        "todo": null,
        "sentence_no": null,
        "begin": "700",
        "end": "704",
        "highlightText": "This",
        "replacements": [],
        "impact": "advanced",
        "categoryHuman": "Intricate text",
        "id": 17,
        "starting_sentence": "Go to [localhost9090",
        "cell_number": 1
    },
    {
        "todo": null,
        "sentence_no": null,
        "begin": "205",
        "end": "206",
        "highlightText": "state,",
        "replacements": [],
        "impact": "advanced",
        "categoryHuman": "Punctuation in compound/complex sentences",
        "id": 18,
        "starting_sentence": "Go to [localhost9090",
        "cell_number": 1
    },
    {
        "todo": null,
        "sentence_no": null,
        "begin": "473",
        "end": "697",
        "highlightText": "modified=232133242234453  From the targets window, click on the endpoint of the node exporter http//localhost9100/metrics, to obtain a text list of all the metrics that are being scraped and that are available to Prometheus.",
        "replacements": [],
        "impact": "advanced",
        "categoryHuman": "Intricate text",
        "id": 20,
        "starting_sentence": "Go to [localhost9090",
        "cell_number": 1
    },
    {
        "todo": null,
        "sentence_no": null,
        "begin": "594",
        "end": "595",
        "highlightText": "metrics,",
        "replacements": [],
        "impact": "advanced",
        "categoryHuman": "Punctuation in compound/complex sentences",
        "id": 19,
        "starting_sentence": "Go to [localhost9090",
        "cell_number": 1
    },
    {
        "todo": null,
        "sentence_no": null,
        "begin": "646",
        "end": "659",
        "highlightText": "being scraped",
        "replacements": [],
        "impact": "advanced",
        "categoryHuman": "Passive voice misuse",
        "id": 21,
        "starting_sentence": "Go to [localhost9090",
        "cell_number": 1
    },
    {
        "todo": "change the wording",
        "sentence_no": "0",
        "begin": "1277",
        "end": "1285",
        "highlightText": "Prior to",
        "replacements": [
            "Before"
        ],
        "impact": "advanced",
        "categoryHuman": "Wordy sentences",
        "id": 22,
        "starting_sentence": "Go to [localhost9090",
        "cell_number": 1
    },
    {
        "todo": null,
        "sentence_no": null,
        "begin": "1093",
        "end": "1093",
        "highlightText": "which",
        "replacements": [],
        "impact": "advanced",
        "categoryHuman": "Punctuation in compound/complex sentences",
        "id": 23,
        "starting_sentence": "Go to [localhost9090",
        "cell_number": 1
    },
    {
        "todo": null,
        "sentence_no": null,
        "begin": "70",
        "end": "75",
        "highlightText": "that everything",
        "replacements": [],
        "impact": "advanced",
        "categoryHuman": "Wordy sentences",
        "id": 25,
        "starting_sentence": "Go to [localhost9090",
        "cell_number": 1
    },
    {
        "todo": null,
        "sentence_no": null,
        "begin": "86",
        "end": "96",
        "highlightText": "was set up",
        "replacements": [],
        "impact": "advanced",
        "categoryHuman": "Passive voice misuse",
        "id": 24,
        "starting_sentence": "Go to [localhost9090",
        "cell_number": 1
    },
    {
        "emotions": [
            {
                "emoji": "\ud83d\udc54",
                "emojiId": "1f454",
                "name": "formal",
                "confidence": 0.994140625
            },
            {
                "emoji": "\ud83e\udd13",
                "emojiId": "1f913",
                "name": "informative",
                "confidence": 0.9921875
            }
        ],
        "action": "emotions",
        "starting_sentence": "Go to [localhost9090",
        "cell_number": 1
    },
    {
        "emotions": [],
        "action": "emotions",
        "starting_sentence": "### Configuring Prom",
        "cell_number": 1
    },
    {
        "todo": null,
        "sentence_no": null,
        "begin": "701",
        "end": "711",
        "highlightText": "is located",
        "replacements": [],
        "impact": "advanced",
        "categoryHuman": "Passive voice misuse",
        "id": 19,
        "starting_sentence": "To track Docker with",
        "cell_number": 1
    },
    {
        "todo": null,
        "sentence_no": null,
        "begin": "118",
        "end": "122",
        "highlightText": "This",
        "replacements": [],
        "impact": "advanced",
        "categoryHuman": "Intricate text",
        "id": 20,
        "starting_sentence": "To track Docker with",
        "cell_number": 1
    },
    {
        "todo": null,
        "sentence_no": null,
        "begin": "177",
        "end": "195",
        "highlightText": "do this by editing",
        "replacements": [],
        "impact": "advanced",
        "categoryHuman": "Wordy sentences",
        "id": 21,
        "starting_sentence": "To track Docker with",
        "cell_number": 1
    },
    {
        "todo": null,
        "sentence_no": null,
        "begin": "597",
        "end": "620",
        "highlightText": "the scraping of metrics",
        "replacements": [],
        "impact": "advanced",
        "categoryHuman": "Wordy sentences",
        "id": 22,
        "starting_sentence": "To track Docker with",
        "cell_number": 1
    },
    {
        "todo": null,
        "sentence_no": null,
        "begin": "348",
        "end": "356",
        "highlightText": "already",
        "replacements": [],
        "impact": "advanced",
        "categoryHuman": "Wordy sentences",
        "id": 24,
        "starting_sentence": "To track Docker with",
        "cell_number": 1
    },
    {
        "todo": "change the spelling",
        "sentence_no": "0",
        "begin": "379",
        "end": "383",
        "highlightText": "sudo",
        "replacements": [],
        "impact": "critical",
        "categoryHuman": "Unknown words",
        "id": 23,
        "starting_sentence": "To track Docker with",
        "cell_number": 1
    },
    {
        "todo": null,
        "sentence_no": null,
        "begin": "75",
        "end": "89",
        "highlightText": "so that we can",
        "replacements": [],
        "impact": "advanced",
        "categoryHuman": "Wordy sentences",
        "id": 25,
        "starting_sentence": "To track Docker with",
        "cell_number": 1
    },
    {
        "todo": null,
        "sentence_no": null,
        "begin": "472",
        "end": "478",
        "highlightText": "to go",
        "replacements": [],
        "impact": "advanced",
        "categoryHuman": "Wordy sentences",
        "id": 26,
        "starting_sentence": "To track Docker with",
        "cell_number": 1
    },
    {
        "emotions": [
            {
                "emoji": "\ud83e\udd13",
                "emojiId": "1f913",
                "name": "informative",
                "confidence": 1.0
            }
        ],
        "action": "emotions",
        "starting_sentence": "To track Docker with",
        "cell_number": 1
    },
    {
        "todo": null,
        "sentence_no": null,
        "begin": "421",
        "end": "421",
        "highlightText": "follows",
        "replacements": [],
        "impact": "advanced",
        "categoryHuman": "Closing punctuation",
        "id": 14,
        "starting_sentence": "For Docker Desktop, ",
        "cell_number": 1
    },
    {
        "todo": null,
        "sentence_no": null,
        "begin": "111",
        "end": "123",
        "highlightText": "will need to",
        "replacements": [],
        "impact": "advanced",
        "categoryHuman": "Wordy sentences",
        "id": 17,
        "starting_sentence": "For Docker Desktop, ",
        "cell_number": 1
    },
    {
        "todo": "correct article usage",
        "sentence_no": "0",
        "begin": "145",
        "end": "145",
        "highlightText": "sudo",
        "replacements": [
            "the "
        ],
        "impact": "critical",
        "categoryHuman": "Determiner use (a/an/the/this, etc.)",
        "id": 15,
        "starting_sentence": "For Docker Desktop, ",
        "cell_number": 1
    },
    {
        "todo": "change the spelling",
        "sentence_no": "0",
        "begin": "145",
        "end": "149",
        "highlightText": "sudo",
        "replacements": [],
        "impact": "critical",
        "categoryHuman": "Unknown words",
        "id": 16,
        "starting_sentence": "For Docker Desktop, ",
        "cell_number": 1
    },
    {
        "todo": "correct your spelling",
        "sentence_no": "0",
        "begin": "414",
        "end": "422",
        "highlightText": "follows'",
        "replacements": [
            "follows"
        ],
        "impact": "critical",
        "categoryHuman": "Confused words",
        "id": 13,
        "starting_sentence": "For Docker Desktop, ",
        "cell_number": 1
    },
    {
        "emotions": [
            {
                "emoji": "\ud83e\udd13",
                "emojiId": "1f913",
                "name": "informative",
                "confidence": 0.998046875
            },
            {
                "emoji": "\u261d\ufe0f",
                "emojiId": "261d",
                "name": "assertive",
                "confidence": 0.4829101562
            }
        ],
        "action": "emotions",
        "starting_sentence": "For Docker Desktop, ",
        "cell_number": 1
    },
    {
        "todo": null,
        "sentence_no": null,
        "begin": "87",
        "end": "87",
        "highlightText": "command",
        "replacements": [],
        "impact": "advanced",
        "categoryHuman": "Closing punctuation",
        "id": 4,
        "starting_sentence": "Now, update the conf",
        "cell_number": 1
    },
    {
        "emotions": [],
        "action": "emotions",
        "starting_sentence": "Now, update the conf",
        "cell_number": 1
    },
    {
        "emotions": [
            {
                "emoji": "\ud83e\udd13",
                "emojiId": "1f913",
                "name": "informative",
                "confidence": 0.9990234375
            }
        ],
        "action": "emotions",
        "starting_sentence": "Observe the Promethe",
        "cell_number": 1
    },
    {
        "todo": null,
        "sentence_no": null,
        "begin": "259",
        "end": "277",
        "highlightText": "here is the result",
        "replacements": [],
        "impact": "advanced",
        "categoryHuman": "Wordy sentences",
        "id": 9,
        "starting_sentence": "Now, we attempt to s",
        "cell_number": 1
    },
    {
        "emotions": [
            {
                "emoji": "\ud83e\udd13",
                "emojiId": "1f913",
                "name": "informative",
                "confidence": 0.9970703125
            }
        ],
        "action": "emotions",
        "starting_sentence": "Now, we attempt to s",
        "cell_number": 1
    },
    {
        "todo": null,
        "sentence_no": null,
        "begin": "1170",
        "end": "1180",
        "highlightText": "is limited",
        "replacements": [],
        "impact": "advanced",
        "categoryHuman": "Passive voice misuse",
        "id": 16,
        "starting_sentence": "## Conclusion At thi",
        "cell_number": 1
    },
    {
        "todo": "change the capitalization",
        "sentence_no": "0",
        "begin": "1248",
        "end": "1258",
        "highlightText": "prometheus",
        "replacements": [
            "Prometheus"
        ],
        "impact": "critical",
        "categoryHuman": "Misspelled words",
        "id": 15,
        "starting_sentence": "## Conclusion At thi",
        "cell_number": 1
    },
    {
        "todo": null,
        "sentence_no": null,
        "begin": "41",
        "end": "69",
        "highlightText": "have a good understanding of",
        "replacements": [],
        "impact": "advanced",
        "categoryHuman": "Wordy sentences",
        "id": 17,
        "starting_sentence": "## Conclusion At thi",
        "cell_number": 1
    },
    {
        "todo": null,
        "sentence_no": null,
        "begin": "263",
        "end": "277",
        "highlightText": "can be updated",
        "replacements": [],
        "impact": "advanced",
        "categoryHuman": "Passive voice misuse",
        "id": 18,
        "starting_sentence": "## Conclusion At thi",
        "cell_number": 1
    },
    {
        "emotions": [
            {
                "emoji": "\ud83e\udd13",
                "emojiId": "1f913",
                "name": "informative",
                "confidence": 1.0
            }
        ],
        "action": "emotions",
        "starting_sentence": "## Conclusion At thi",
        "cell_number": 1
    },
    {
        "num_of_corrections": 171
    }
]