[
    {
        "todo": "correct your spelling",
        "sentence_no": "0",
        "begin": "17",
        "end": "25",
        "highlightText": "Formats'",
        "replacements": [
            "Formats"
        ],
        "impact": "critical",
        "categoryHuman": "Confused words",
        "id": 4,
        "starting_sentence": "# Data and File Form",
        "cell_number": 1
    },
    {
        "emotions": [],
        "action": "emotions",
        "starting_sentence": "# Data and File Form",
        "cell_number": 1
    },
    {
        "todo": "change preposition",
        "sentence_no": "0",
        "begin": "14",
        "end": "16",
        "highlightText": "in",
        "replacements": [
            "on"
        ],
        "impact": "critical",
        "categoryHuman": "Wrong or missing prepositions",
        "id": 5,
        "starting_sentence": "When working in proj",
        "cell_number": 1
    },
    {
        "todo": null,
        "sentence_no": null,
        "begin": "112",
        "end": "112",
        "highlightText": "including",
        "replacements": [],
        "impact": "advanced",
        "categoryHuman": "Punctuation in compound/complex sentences",
        "id": 6,
        "starting_sentence": "When working in proj",
        "cell_number": 1
    },
    {
        "todo": null,
        "sentence_no": null,
        "begin": "168",
        "end": "170",
        "highlightText": "In",
        "replacements": [],
        "impact": "advanced",
        "categoryHuman": "Punctuation in compound/complex sentences",
        "id": 7,
        "starting_sentence": "When working in proj",
        "cell_number": 1
    },
    {
        "emotions": [
            {
                "emoji": "\ud83e\udd1d",
                "emojiId": "1f91d",
                "name": "confident",
                "confidence": 1.0
            },
            {
                "emoji": "\ud83c\udfaf",
                "emojiId": "1f3af",
                "name": "direct",
                "confidence": 0.9633789062
            }
        ],
        "action": "emotions",
        "starting_sentence": "When working in proj",
        "cell_number": 1
    },
    {
        "emotions": [],
        "action": "emotions",
        "starting_sentence": "## CSV",
        "cell_number": 1
    },
    {
        "todo": null,
        "sentence_no": null,
        "begin": "880",
        "end": "880",
        "highlightText": "p",
        "replacements": [],
        "impact": "advanced",
        "categoryHuman": "Closing punctuation",
        "id": 15,
        "starting_sentence": " <font size=+1 CSV (",
        "cell_number": 1
    },
    {
        "todo": "change preposition",
        "sentence_no": "0",
        "begin": "667",
        "end": "669",
        "highlightText": "by",
        "replacements": [
            "in"
        ],
        "impact": "critical",
        "categoryHuman": "Wrong or missing prepositions",
        "id": 16,
        "starting_sentence": " <font size=+1 CSV (",
        "cell_number": 1
    },
    {
        "todo": null,
        "sentence_no": null,
        "begin": "426",
        "end": "438",
        "highlightText": "also called",
        "replacements": [],
        "impact": "advanced",
        "categoryHuman": "Wordy sentences",
        "id": 18,
        "starting_sentence": " <font size=+1 CSV (",
        "cell_number": 1
    },
    {
        "todo": "change the spelling",
        "sentence_no": "0",
        "begin": "438",
        "end": "441",
        "highlightText": "tsv",
        "replacements": [],
        "impact": "critical",
        "categoryHuman": "Unknown words",
        "id": 17,
        "starting_sentence": " <font size=+1 CSV (",
        "cell_number": 1
    },
    {
        "todo": null,
        "sentence_no": null,
        "begin": "131",
        "end": "144",
        "highlightText": "a very common",
        "replacements": [],
        "impact": "advanced",
        "categoryHuman": "Word choice",
        "id": 19,
        "starting_sentence": " <font size=+1 CSV (",
        "cell_number": 1
    },
    {
        "todo": "add the comma(s)",
        "sentence_no": "0",
        "begin": "264",
        "end": "277",
        "highlightText": "in this case",
        "replacements": [
            ", in this case,"
        ],
        "impact": "critical",
        "categoryHuman": "Comma misuse within clauses",
        "id": 20,
        "starting_sentence": " <font size=+1 CSV (",
        "cell_number": 1
    },
    {
        "todo": null,
        "sentence_no": null,
        "begin": "278",
        "end": "287",
        "highlightText": "is called",
        "replacements": [],
        "impact": "advanced",
        "categoryHuman": "Passive voice misuse",
        "id": 21,
        "starting_sentence": " <font size=+1 CSV (",
        "cell_number": 1
    },
    {
        "todo": null,
        "sentence_no": null,
        "begin": "589",
        "end": "590",
        "highlightText": "delimiter,",
        "replacements": [],
        "impact": "advanced",
        "categoryHuman": "Punctuation in compound/complex sentences",
        "id": 22,
        "starting_sentence": " <font size=+1 CSV (",
        "cell_number": 1
    },
    {
        "todo": null,
        "sentence_no": null,
        "begin": "591",
        "end": "595",
        "highlightText": "and",
        "replacements": [],
        "impact": "advanced",
        "categoryHuman": "Wordy sentences",
        "id": 23,
        "starting_sentence": " <font size=+1 CSV (",
        "cell_number": 1
    },
    {
        "todo": null,
        "sentence_no": null,
        "begin": "709",
        "end": "709",
        "highlightText": "Usually",
        "replacements": [],
        "impact": "advanced",
        "categoryHuman": "Punctuation in compound/complex sentences",
        "id": 26,
        "starting_sentence": " <font size=+1 CSV (",
        "cell_number": 1
    },
    {
        "todo": null,
        "sentence_no": null,
        "begin": "782",
        "end": "782",
        "highlightText": "etc",
        "replacements": [],
        "impact": "advanced",
        "categoryHuman": "Comma misuse within clauses",
        "id": 24,
        "starting_sentence": " <font size=+1 CSV (",
        "cell_number": 1
    },
    {
        "todo": null,
        "sentence_no": null,
        "begin": "783",
        "end": "783",
        "highlightText": ") ",
        "replacements": [],
        "impact": "advanced",
        "categoryHuman": "Punctuation in compound/complex sentences",
        "id": 27,
        "starting_sentence": " <font size=+1 CSV (",
        "cell_number": 1
    },
    {
        "todo": null,
        "sentence_no": null,
        "begin": "809",
        "end": "816",
        "highlightText": ", hence",
        "replacements": [],
        "impact": "advanced",
        "categoryHuman": "Punctuation in compound/complex sentences",
        "id": 25,
        "starting_sentence": " <font size=+1 CSV (",
        "cell_number": 1
    },
    {
        "emotions": [
            {
                "emoji": "\ud83d\ude10",
                "emojiId": "1f610",
                "name": "neutral",
                "confidence": 1.0
            }
        ],
        "action": "emotions",
        "starting_sentence": " <font size=+1 CSV (",
        "cell_number": 1
    },
    {
        "todo": "correct your spelling",
        "sentence_no": "0",
        "begin": "14",
        "end": "20",
        "highlightText": "files'",
        "replacements": [
            "files"
        ],
        "impact": "critical",
        "categoryHuman": "Confused words",
        "id": 4,
        "starting_sentence": "### Open CSV files",
        "cell_number": 1
    },
    {
        "emotions": [],
        "action": "emotions",
        "starting_sentence": "### Open CSV files",
        "cell_number": 1
    },
    {
        "todo": null,
        "sentence_no": null,
        "begin": "208",
        "end": "214",
        "highlightText": "is set",
        "replacements": [],
        "impact": "advanced",
        "categoryHuman": "Passive voice misuse",
        "id": 9,
        "starting_sentence": "Python counts with a",
        "cell_number": 1
    },
    {
        "todo": "correct your spelling",
        "sentence_no": "0",
        "begin": "260",
        "end": "263",
        "highlightText": "csv",
        "replacements": [
            "CSV"
        ],
        "impact": "critical",
        "categoryHuman": "Misspelled words",
        "id": 11,
        "starting_sentence": "Python counts with a",
        "cell_number": 1
    },
    {
        "todo": "correct your spelling",
        "sentence_no": "0",
        "begin": "299",
        "end": "302",
        "highlightText": "csv",
        "replacements": [
            "CSV"
        ],
        "impact": "critical",
        "categoryHuman": "Misspelled words",
        "id": 12,
        "starting_sentence": "Python counts with a",
        "cell_number": 1
    },
    {
        "todo": "change the article",
        "sentence_no": "0",
        "begin": "347",
        "end": "350",
        "highlightText": "an iterable",
        "replacements": [
            ""
        ],
        "impact": "critical",
        "categoryHuman": "Determiner use (a/an/the/this, etc.)",
        "id": 10,
        "starting_sentence": "Python counts with a",
        "cell_number": 1
    },
    {
        "todo": null,
        "sentence_no": null,
        "begin": "22",
        "end": "40",
        "highlightText": "library called csv",
        "replacements": [],
        "impact": "advanced",
        "categoryHuman": "Wordy sentences",
        "id": 14,
        "starting_sentence": "Python counts with a",
        "cell_number": 1
    },
    {
        "todo": "change the spelling",
        "sentence_no": "0",
        "begin": "37",
        "end": "40",
        "highlightText": "csv",
        "replacements": [],
        "impact": "critical",
        "categoryHuman": "Unknown words",
        "id": 13,
        "starting_sentence": "Python counts with a",
        "cell_number": 1
    },
    {
        "emotions": [
            {
                "emoji": "\ud83e\udd13",
                "emojiId": "1f913",
                "name": "informative",
                "confidence": 1.0
            }
        ],
        "action": "emotions",
        "starting_sentence": "Python counts with a",
        "cell_number": 1
    },
    {
        "todo": null,
        "sentence_no": null,
        "begin": "21",
        "end": "21",
        "highlightText": "files",
        "replacements": [],
        "impact": "advanced",
        "categoryHuman": "Closing punctuation",
        "id": 5,
        "starting_sentence": "### Create CSV files",
        "cell_number": 1
    },
    {
        "todo": "correct your spelling",
        "sentence_no": "0",
        "begin": "16",
        "end": "22",
        "highlightText": "files'",
        "replacements": [
            "files"
        ],
        "impact": "critical",
        "categoryHuman": "Confused words",
        "id": 4,
        "starting_sentence": "### Create CSV files",
        "cell_number": 1
    },
    {
        "emotions": [],
        "action": "emotions",
        "starting_sentence": "### Create CSV files",
        "cell_number": 1
    },
    {
        "todo": "correct your spelling",
        "sentence_no": "0",
        "begin": "181",
        "end": "184",
        "highlightText": "csv",
        "replacements": [
            "CSV"
        ],
        "impact": "critical",
        "categoryHuman": "Misspelled words",
        "id": 9,
        "starting_sentence": "The same library can",
        "cell_number": 1
    },
    {
        "todo": null,
        "sentence_no": null,
        "begin": "217",
        "end": "218",
        "highlightText": ") ",
        "replacements": [],
        "impact": "advanced",
        "categoryHuman": "Closing punctuation",
        "id": 10,
        "starting_sentence": "The same library can",
        "cell_number": 1
    },
    {
        "todo": null,
        "sentence_no": null,
        "begin": "1",
        "end": "29",
        "highlightText": "The same library can be used",
        "replacements": [],
        "impact": "advanced",
        "categoryHuman": "Passive voice misuse",
        "id": 12,
        "starting_sentence": "The same library can",
        "cell_number": 1
    },
    {
        "todo": "correct your spelling",
        "sentence_no": "0",
        "begin": "42",
        "end": "45",
        "highlightText": "csv",
        "replacements": [
            "CSV"
        ],
        "impact": "critical",
        "categoryHuman": "Misspelled words",
        "id": 11,
        "starting_sentence": "The same library can",
        "cell_number": 1
    },
    {
        "emotions": [
            {
                "emoji": "\u261d\ufe0f",
                "emojiId": "261d",
                "name": "assertive",
                "confidence": 0.984375
            },
            {
                "emoji": "\ud83d\udc54",
                "emojiId": "1f454",
                "name": "formal",
                "confidence": 0.6987304688
            },
            {
                "emoji": "\ud83e\udd13",
                "emojiId": "1f913",
                "name": "informative",
                "confidence": 0.5336914062
            }
        ],
        "action": "emotions",
        "starting_sentence": "The same library can",
        "cell_number": 1
    },
    {
        "todo": "correct your spelling",
        "sentence_no": "0",
        "begin": "337",
        "end": "346",
        "highlightText": "writerows",
        "replacements": [
            "writers"
        ],
        "impact": "critical",
        "categoryHuman": "Misspelled words",
        "id": 10,
        "starting_sentence": "As opposed to readin",
        "cell_number": 1
    },
    {
        "todo": "change the spelling",
        "sentence_no": "0",
        "begin": "362",
        "end": "371",
        "highlightText": "iterables",
        "replacements": [],
        "impact": "critical",
        "categoryHuman": "Unknown words",
        "id": 11,
        "starting_sentence": "As opposed to readin",
        "cell_number": 1
    },
    {
        "todo": "correct subject-verb agreement",
        "sentence_no": "0",
        "begin": "390",
        "end": "395",
        "highlightText": "parse",
        "replacements": [
            "parses"
        ],
        "impact": "critical",
        "categoryHuman": "Faulty subject-verb agreement",
        "id": 12,
        "starting_sentence": "As opposed to readin",
        "cell_number": 1
    },
    {
        "todo": "add a\u00a0hyphen",
        "sentence_no": "0",
        "begin": "408",
        "end": "423",
        "highlightText": "comma separated",
        "replacements": [
            "comma-separated"
        ],
        "impact": "critical",
        "categoryHuman": "Misspelled words",
        "id": 14,
        "starting_sentence": "As opposed to readin",
        "cell_number": 1
    },
    {
        "todo": null,
        "sentence_no": null,
        "begin": "427",
        "end": "429",
        "highlightText": "So",
        "replacements": [],
        "impact": "advanced",
        "categoryHuman": "Punctuation in compound/complex sentences",
        "id": 13,
        "starting_sentence": "As opposed to readin",
        "cell_number": 1
    },
    {
        "todo": null,
        "sentence_no": null,
        "begin": "255",
        "end": "257",
        "highlightText": "The",
        "replacements": [],
        "impact": "advanced",
        "categoryHuman": "Punctuation in compound/complex sentences",
        "id": 15,
        "starting_sentence": "As opposed to readin",
        "cell_number": 1
    },
    {
        "todo": "correct your spelling",
        "sentence_no": "0",
        "begin": "448",
        "end": "453",
        "highlightText": "list'",
        "replacements": [
            "list"
        ],
        "impact": "critical",
        "categoryHuman": "Confused words",
        "id": 9,
        "starting_sentence": "As opposed to readin",
        "cell_number": 1
    },
    {
        "emotions": [
            {
                "emoji": "\ud83d\udc54",
                "emojiId": "1f454",
                "name": "formal",
                "confidence": 0.9873046875
            },
            {
                "emoji": "\u261d\ufe0f",
                "emojiId": "261d",
                "name": "assertive",
                "confidence": 0.9462890625
            }
        ],
        "action": "emotions",
        "starting_sentence": "As opposed to readin",
        "cell_number": 1
    },
    {
        "todo": "correct your spelling",
        "sentence_no": "0",
        "begin": "21",
        "end": "24",
        "highlightText": "csv",
        "replacements": [
            "CSV"
        ],
        "impact": "critical",
        "categoryHuman": "Misspelled words",
        "id": 4,
        "starting_sentence": "We can create a new ",
        "cell_number": 1
    },
    {
        "todo": null,
        "sentence_no": null,
        "begin": "84",
        "end": "84",
        "highlightText": "dog",
        "replacements": [],
        "impact": "advanced",
        "categoryHuman": "Closing punctuation",
        "id": 5,
        "starting_sentence": "We can create a new ",
        "cell_number": 1
    },
    {
        "emotions": [],
        "action": "emotions",
        "starting_sentence": "We can create a new ",
        "cell_number": 1
    },
    {
        "todo": null,
        "sentence_no": null,
        "begin": "138",
        "end": "138",
        "highlightText": "files",
        "replacements": [],
        "impact": "advanced",
        "categoryHuman": "Closing punctuation",
        "id": 8,
        "starting_sentence": "Notice the differenc",
        "cell_number": 1
    },
    {
        "todo": "correct your spelling",
        "sentence_no": "0",
        "begin": "31",
        "end": "39",
        "highlightText": "writerow",
        "replacements": [
            "writers",
            "writer"
        ],
        "impact": "critical",
        "categoryHuman": "Misspelled words",
        "id": 9,
        "starting_sentence": "Notice the differenc",
        "cell_number": 1
    },
    {
        "todo": "correct your spelling",
        "sentence_no": "0",
        "begin": "44",
        "end": "53",
        "highlightText": "writerows",
        "replacements": [
            "writers"
        ],
        "impact": "critical",
        "categoryHuman": "Misspelled words",
        "id": 10,
        "starting_sentence": "Notice the differenc",
        "cell_number": 1
    },
    {
        "todo": "correct your spelling",
        "sentence_no": "0",
        "begin": "133",
        "end": "139",
        "highlightText": "files'",
        "replacements": [
            "files"
        ],
        "impact": "critical",
        "categoryHuman": "Confused words",
        "id": 7,
        "starting_sentence": "Notice the differenc",
        "cell_number": 1
    },
    {
        "emotions": [],
        "action": "emotions",
        "starting_sentence": "Notice the differenc",
        "cell_number": 1
    },
    {
        "emotions": [],
        "action": "emotions",
        "starting_sentence": "## JSON ",
        "cell_number": 1
    },
    {
        "todo": "remove the phrase",
        "sentence_no": "0",
        "begin": "328",
        "end": "337",
        "highlightText": "actually",
        "replacements": [
            ""
        ],
        "impact": "advanced",
        "categoryHuman": "Wordy sentences",
        "id": 11,
        "starting_sentence": " <font size=+1 JSON ",
        "cell_number": 1
    },
    {
        "todo": null,
        "sentence_no": null,
        "begin": "164",
        "end": "170",
        "highlightText": "useful",
        "replacements": [],
        "impact": "advanced",
        "categoryHuman": "Word choice",
        "id": 13,
        "starting_sentence": " <font size=+1 JSON ",
        "cell_number": 1
    },
    {
        "todo": "correct your spelling",
        "sentence_no": "0",
        "begin": "161",
        "end": "163",
        "highlightText": "as",
        "replacements": [
            "a"
        ],
        "impact": "critical",
        "categoryHuman": "Confused words",
        "id": 12,
        "starting_sentence": " <font size=+1 JSON ",
        "cell_number": 1
    },
    {
        "emotions": [
            {
                "emoji": "\u261d\ufe0f",
                "emojiId": "261d",
                "name": "assertive",
                "confidence": 0.99609375
            },
            {
                "emoji": "\ud83d\udc54",
                "emojiId": "1f454",
                "name": "formal",
                "confidence": 0.9633789062
            }
        ],
        "action": "emotions",
        "starting_sentence": " <font size=+1 JSON ",
        "cell_number": 1
    },
    {
        "todo": null,
        "sentence_no": null,
        "begin": "71",
        "end": "71",
        "highlightText": "and",
        "replacements": [],
        "impact": "advanced",
        "categoryHuman": "Punctuation in compound/complex sentences",
        "id": 6,
        "starting_sentence": "JSON format is very ",
        "cell_number": 1
    },
    {
        "todo": null,
        "sentence_no": null,
        "begin": "116",
        "end": "116",
        "highlightText": "key",
        "replacements": [],
        "impact": "advanced",
        "categoryHuman": "Closing punctuation",
        "id": 5,
        "starting_sentence": "JSON format is very ",
        "cell_number": 1
    },
    {
        "todo": "correct your spelling",
        "sentence_no": "0",
        "begin": "113",
        "end": "117",
        "highlightText": "key'",
        "replacements": [
            "key"
        ],
        "impact": "critical",
        "categoryHuman": "Confused words",
        "id": 4,
        "starting_sentence": "JSON format is very ",
        "cell_number": 1
    },
    {
        "emotions": [],
        "action": "emotions",
        "starting_sentence": "JSON format is very ",
        "cell_number": 1
    },
    {
        "todo": null,
        "sentence_no": null,
        "begin": "20",
        "end": "20",
        "highlightText": "files",
        "replacements": [],
        "impact": "advanced",
        "categoryHuman": "Closing punctuation",
        "id": 4,
        "starting_sentence": "### Read JSON files",
        "cell_number": 1
    },
    {
        "emotions": [],
        "action": "emotions",
        "starting_sentence": "### Read JSON files",
        "cell_number": 1
    },
    {
        "todo": "change the spelling",
        "sentence_no": "0",
        "begin": "32",
        "end": "36",
        "highlightText": "json",
        "replacements": [],
        "impact": "critical",
        "categoryHuman": "Unknown words",
        "id": 5,
        "starting_sentence": "Python offers a libr",
        "cell_number": 1
    },
    {
        "todo": null,
        "sentence_no": null,
        "begin": "100",
        "end": "100",
        "highlightText": "file",
        "replacements": [],
        "impact": "advanced",
        "categoryHuman": "Closing punctuation",
        "id": 6,
        "starting_sentence": "Python offers a libr",
        "cell_number": 1
    },
    {
        "todo": "correct your spelling",
        "sentence_no": "0",
        "begin": "96",
        "end": "101",
        "highlightText": "file'",
        "replacements": [
            "file"
        ],
        "impact": "critical",
        "categoryHuman": "Confused words",
        "id": 4,
        "starting_sentence": "Python offers a libr",
        "cell_number": 1
    },
    {
        "emotions": [],
        "action": "emotions",
        "starting_sentence": "Python offers a libr",
        "cell_number": 1
    },
    {
        "todo": null,
        "sentence_no": null,
        "begin": "188",
        "end": "188",
        "highlightText": "method",
        "replacements": [],
        "impact": "advanced",
        "categoryHuman": "Closing punctuation",
        "id": 9,
        "starting_sentence": "The syntax is very s",
        "cell_number": 1
    },
    {
        "emotions": [
            {
                "emoji": "\ud83d\udc54",
                "emojiId": "1f454",
                "name": "formal",
                "confidence": 0.9799804688
            },
            {
                "emoji": "\u261d\ufe0f",
                "emojiId": "261d",
                "name": "assertive",
                "confidence": 0.650390625
            }
        ],
        "action": "emotions",
        "starting_sentence": "The syntax is very s",
        "cell_number": 1
    },
    {
        "todo": null,
        "sentence_no": null,
        "begin": "13",
        "end": "14",
        "highlightText": "that,",
        "replacements": [],
        "impact": "advanced",
        "categoryHuman": "Punctuation in compound/complex sentences",
        "id": 6,
        "starting_sentence": "Observe that, whatev",
        "cell_number": 1
    },
    {
        "todo": null,
        "sentence_no": null,
        "begin": "48",
        "end": "48",
        "highlightText": "dictionary",
        "replacements": [],
        "impact": "advanced",
        "categoryHuman": "Closing punctuation",
        "id": 5,
        "starting_sentence": "Observe that, whatev",
        "cell_number": 1
    },
    {
        "todo": "correct your spelling",
        "sentence_no": "0",
        "begin": "38",
        "end": "49",
        "highlightText": "dictionary'",
        "replacements": [
            "dictionary"
        ],
        "impact": "critical",
        "categoryHuman": "Confused words",
        "id": 4,
        "starting_sentence": "Observe that, whatev",
        "cell_number": 1
    },
    {
        "emotions": [],
        "action": "emotions",
        "starting_sentence": "Observe that, whatev",
        "cell_number": 1
    },
    {
        "todo": null,
        "sentence_no": null,
        "begin": "22",
        "end": "22",
        "highlightText": "files",
        "replacements": [],
        "impact": "advanced",
        "categoryHuman": "Closing punctuation",
        "id": 4,
        "starting_sentence": "### Create JSON file",
        "cell_number": 1
    },
    {
        "emotions": [],
        "action": "emotions",
        "starting_sentence": "### Create JSON file",
        "cell_number": 1
    },
    {
        "todo": "correct your spelling",
        "sentence_no": "0",
        "begin": "15",
        "end": "19",
        "highlightText": "json",
        "replacements": [
            "JSON"
        ],
        "impact": "critical",
        "categoryHuman": "Misspelled words",
        "id": 11,
        "starting_sentence": "We can create json f",
        "cell_number": 1
    },
    {
        "todo": null,
        "sentence_no": null,
        "begin": "106",
        "end": "106",
        "highlightText": "in",
        "replacements": [],
        "impact": "advanced",
        "categoryHuman": "Punctuation in compound/complex sentences",
        "id": 12,
        "starting_sentence": "We can create json f",
        "cell_number": 1
    },
    {
        "todo": null,
        "sentence_no": null,
        "begin": "119",
        "end": "119",
        "highlightText": "case",
        "replacements": [],
        "impact": "advanced",
        "categoryHuman": "Punctuation in compound/complex sentences",
        "id": 13,
        "starting_sentence": "We can create json f",
        "cell_number": 1
    },
    {
        "todo": null,
        "sentence_no": null,
        "begin": "176",
        "end": "177",
        "highlightText": "use,",
        "replacements": [],
        "impact": "advanced",
        "categoryHuman": "Punctuation in compound/complex sentences",
        "id": 14,
        "starting_sentence": "We can create json f",
        "cell_number": 1
    },
    {
        "emotions": [
            {
                "emoji": "\ud83e\udd13",
                "emojiId": "1f913",
                "name": "informative",
                "confidence": 0.9658203125
            }
        ],
        "action": "emotions",
        "starting_sentence": "We can create json f",
        "cell_number": 1
    },
    {
        "todo": "correct your spelling",
        "sentence_no": "0",
        "begin": "47",
        "end": "51",
        "highlightText": "json",
        "replacements": [
            "JSON"
        ],
        "impact": "critical",
        "categoryHuman": "Misspelled words",
        "id": 4,
        "starting_sentence": "Observe in your dire",
        "cell_number": 1
    },
    {
        "todo": null,
        "sentence_no": null,
        "begin": "78",
        "end": "78",
        "highlightText": "JSON_test.json",
        "replacements": [],
        "impact": "advanced",
        "categoryHuman": "Closing punctuation",
        "id": 5,
        "starting_sentence": "Observe in your dire",
        "cell_number": 1
    },
    {
        "emotions": [],
        "action": "emotions",
        "starting_sentence": "Observe in your dire",
        "cell_number": 1
    },
    {
        "todo": "correct your spelling",
        "sentence_no": "0",
        "begin": "40",
        "end": "44",
        "highlightText": "json",
        "replacements": [
            "JSON"
        ],
        "impact": "critical",
        "categoryHuman": "Misspelled words",
        "id": 5,
        "starting_sentence": "We can also have a s",
        "cell_number": 1
    },
    {
        "todo": null,
        "sentence_no": null,
        "begin": "57",
        "end": "57",
        "highlightText": "it",
        "replacements": [],
        "impact": "advanced",
        "categoryHuman": "Closing punctuation",
        "id": 6,
        "starting_sentence": "We can also have a s",
        "cell_number": 1
    },
    {
        "todo": "correct your spelling",
        "sentence_no": "0",
        "begin": "55",
        "end": "58",
        "highlightText": "it'",
        "replacements": [
            "it"
        ],
        "impact": "critical",
        "categoryHuman": "Confused words",
        "id": 4,
        "starting_sentence": "We can also have a s",
        "cell_number": 1
    },
    {
        "emotions": [],
        "action": "emotions",
        "starting_sentence": "We can also have a s",
        "cell_number": 1
    },
    {
        "todo": "correct your spelling",
        "sentence_no": "0",
        "begin": "73",
        "end": "77",
        "highlightText": "json",
        "replacements": [
            "JSON"
        ],
        "impact": "critical",
        "categoryHuman": "Misspelled words",
        "id": 7,
        "starting_sentence": "Be careful with the ",
        "cell_number": 1
    },
    {
        "emotions": [],
        "action": "emotions",
        "starting_sentence": "Be careful with the ",
        "cell_number": 1
    },
    {
        "todo": null,
        "sentence_no": null,
        "begin": "75",
        "end": "75",
        "highlightText": "method",
        "replacements": [],
        "impact": "advanced",
        "categoryHuman": "Closing punctuation",
        "id": 4,
        "starting_sentence": "We do the opposite (",
        "cell_number": 1
    },
    {
        "emotions": [],
        "action": "emotions",
        "starting_sentence": "We do the opposite (",
        "cell_number": 1
    },
    {
        "emotions": [],
        "action": "emotions",
        "starting_sentence": "# YAML",
        "cell_number": 1
    },
    {
        "todo": null,
        "sentence_no": null,
        "begin": "272",
        "end": "272",
        "highlightText": "font",
        "replacements": [],
        "impact": "advanced",
        "categoryHuman": "Closing punctuation",
        "id": 9,
        "starting_sentence": "YAML is a data seria",
        "cell_number": 1
    },
    {
        "todo": "remove the phrase",
        "sentence_no": "0",
        "begin": "112",
        "end": "124",
        "highlightText": "In fact,",
        "replacements": [
            "You"
        ],
        "impact": "advanced",
        "categoryHuman": "Wordy sentences",
        "id": 10,
        "starting_sentence": "YAML is a data seria",
        "cell_number": 1
    },
    {
        "todo": null,
        "sentence_no": null,
        "begin": "52",
        "end": "57",
        "highlightText": "that it",
        "replacements": [],
        "impact": "advanced",
        "categoryHuman": "Wordy sentences",
        "id": 11,
        "starting_sentence": "YAML is a data seria",
        "cell_number": 1
    },
    {
        "emotions": [
            {
                "emoji": "\u261d\ufe0f",
                "emojiId": "261d",
                "name": "assertive",
                "confidence": 0.998046875
            },
            {
                "emoji": "\ud83e\udd1d",
                "emojiId": "1f91d",
                "name": "confident",
                "confidence": 0.4946289062
            }
        ],
        "action": "emotions",
        "starting_sentence": "YAML is a data seria",
        "cell_number": 1
    },
    {
        "todo": null,
        "sentence_no": null,
        "begin": "36",
        "end": "36",
        "highlightText": "is",
        "replacements": [],
        "impact": "advanced",
        "categoryHuman": "Incomplete sentences",
        "id": 9,
        "starting_sentence": "The main advantage o",
        "cell_number": 1
    },
    {
        "emotions": [
            {
                "emoji": "\ud83e\udd1d",
                "emojiId": "1f91d",
                "name": "confident",
                "confidence": 0.9990234375
            },
            {
                "emoji": "\ud83c\udfaf",
                "emojiId": "1f3af",
                "name": "direct",
                "confidence": 0.966796875
            }
        ],
        "action": "emotions",
        "starting_sentence": "The main advantage o",
        "cell_number": 1
    },
    {
        "todo": "correct your spelling",
        "sentence_no": "0",
        "begin": "427",
        "end": "435",
        "highlightText": "keyvalue",
        "replacements": [
            "key-value",
            "key value"
        ],
        "impact": "critical",
        "categoryHuman": "Misspelled words",
        "id": 12,
        "starting_sentence": "Observe that the bas",
        "cell_number": 1
    },
    {
        "todo": "remove the space",
        "sentence_no": "0",
        "begin": "469",
        "end": "474",
        "highlightText": "Person     name",
        "replacements": [
            " "
        ],
        "impact": "critical",
        "categoryHuman": "Improper formatting",
        "id": 13,
        "starting_sentence": "Observe that the bas",
        "cell_number": 1
    },
    {
        "todo": "remove the space",
        "sentence_no": "0",
        "begin": "483",
        "end": "488",
        "highlightText": "Ivan     surname",
        "replacements": [
            " "
        ],
        "impact": "critical",
        "categoryHuman": "Improper formatting",
        "id": 14,
        "starting_sentence": "Observe that the bas",
        "cell_number": 1
    },
    {
        "todo": "add an\u00a0article",
        "sentence_no": "0",
        "begin": "554",
        "end": "554",
        "highlightText": "indentation",
        "replacements": [
            "the "
        ],
        "impact": "critical",
        "categoryHuman": "Determiner use (a/an/the/this, etc.)",
        "id": 11,
        "starting_sentence": "Observe that the bas",
        "cell_number": 1
    },
    {
        "todo": "correct your spelling",
        "sentence_no": "0",
        "begin": "126",
        "end": "134",
        "highlightText": "keyvalue",
        "replacements": [
            "key-value",
            "key value"
        ],
        "impact": "critical",
        "categoryHuman": "Misspelled words",
        "id": 17,
        "starting_sentence": "Observe that the bas",
        "cell_number": 1
    },
    {
        "todo": "remove the space",
        "sentence_no": "0",
        "begin": "139",
        "end": "141",
        "highlightText": "pair  key",
        "replacements": [
            " "
        ],
        "impact": "critical",
        "categoryHuman": "Improper formatting",
        "id": 19,
        "starting_sentence": "Observe that the bas",
        "cell_number": 1
    },
    {
        "todo": "add a\u00a0hyphen",
        "sentence_no": "0",
        "begin": "139",
        "end": "152",
        "highlightText": "key value",
        "replacements": [
            " key-value "
        ],
        "impact": "critical",
        "categoryHuman": "Misspelled words",
        "id": 18,
        "starting_sentence": "Observe that the bas",
        "cell_number": 1
    },
    {
        "todo": null,
        "sentence_no": null,
        "begin": "150",
        "end": "152",
        "highlightText": "For",
        "replacements": [],
        "impact": "advanced",
        "categoryHuman": "Punctuation in compound/complex sentences",
        "id": 16,
        "starting_sentence": "Observe that the bas",
        "cell_number": 1
    },
    {
        "todo": null,
        "sentence_no": null,
        "begin": "163",
        "end": "165",
        "highlightText": "example",
        "replacements": [],
        "impact": "advanced",
        "categoryHuman": "Punctuation in compound/complex sentences",
        "id": 15,
        "starting_sentence": "Observe that the bas",
        "cell_number": 1
    },
    {
        "emotions": [
            {
                "emoji": "\ud83e\udd13",
                "emojiId": "1f913",
                "name": "informative",
                "confidence": 0.9970703125
            }
        ],
        "action": "emotions",
        "starting_sentence": "Observe that the bas",
        "cell_number": 1
    },
    {
        "todo": "change the spelling",
        "sentence_no": "0",
        "begin": "199",
        "end": "203",
        "highlightText": "yaml",
        "replacements": [],
        "impact": "critical",
        "categoryHuman": "Unknown words",
        "id": 5,
        "starting_sentence": "You can look for doc",
        "cell_number": 1
    },
    {
        "todo": "change the spelling",
        "sentence_no": "0",
        "begin": "18",
        "end": "27",
        "highlightText": "docs-yaml",
        "replacements": [],
        "impact": "critical",
        "categoryHuman": "Unknown words",
        "id": 6,
        "starting_sentence": "You can look for doc",
        "cell_number": 1
    },
    {
        "todo": null,
        "sentence_no": null,
        "begin": "132",
        "end": "139",
        "highlightText": "or not",
        "replacements": [],
        "impact": "advanced",
        "categoryHuman": "Wordy sentences",
        "id": 7,
        "starting_sentence": "You can look for doc",
        "cell_number": 1
    },
    {
        "emotions": [
            {
                "emoji": "\ud83e\udd13",
                "emojiId": "1f913",
                "name": "informative",
                "confidence": 0.986328125
            },
            {
                "emoji": "\u261d\ufe0f",
                "emojiId": "261d",
                "name": "assertive",
                "confidence": 0.4885253906
            }
        ],
        "action": "emotions",
        "starting_sentence": "You can look for doc",
        "cell_number": 1
    },
    {
        "todo": "correct your spelling",
        "sentence_no": "0",
        "begin": "108",
        "end": "116",
        "highlightText": "keyvalue",
        "replacements": [
            "key-value",
            "key value"
        ],
        "impact": "critical",
        "categoryHuman": "Misspelled words",
        "id": 7,
        "starting_sentence": "One more thing you c",
        "cell_number": 1
    },
    {
        "todo": "add an\u00a0article",
        "sentence_no": "0",
        "begin": "53",
        "end": "57",
        "highlightText": "List",
        "replacements": [
            "The list"
        ],
        "impact": "critical",
        "categoryHuman": "Determiner use (a/an/the/this, etc.)",
        "id": 8,
        "starting_sentence": "One more thing you c",
        "cell_number": 1
    },
    {
        "todo": null,
        "sentence_no": null,
        "begin": "365",
        "end": "375",
        "highlightText": "be written",
        "replacements": [],
        "impact": "advanced",
        "categoryHuman": "Passive voice misuse",
        "id": 10,
        "starting_sentence": "One more thing you c",
        "cell_number": 1
    },
    {
        "todo": null,
        "sentence_no": null,
        "begin": "416",
        "end": "417",
        "highlightText": "] ",
        "replacements": [],
        "impact": "advanced",
        "categoryHuman": "Closing punctuation",
        "id": 9,
        "starting_sentence": "One more thing you c",
        "cell_number": 1
    },
    {
        "todo": "correct subject-verb agreement",
        "sentence_no": "0",
        "begin": "42",
        "end": "45",
        "highlightText": "are",
        "replacements": [
            "is"
        ],
        "impact": "critical",
        "categoryHuman": "Faulty subject-verb agreement",
        "id": 11,
        "starting_sentence": "One more thing you c",
        "cell_number": 1
    },
    {
        "emotions": [
            {
                "emoji": "\ud83c\udfaf",
                "emojiId": "1f3af",
                "name": "direct",
                "confidence": 0.9951171875
            },
            {
                "emoji": "\ud83e\udd1d",
                "emojiId": "1f91d",
                "name": "confident",
                "confidence": 0.8959960938
            }
        ],
        "action": "emotions",
        "starting_sentence": "One more thing you c",
        "cell_number": 1
    },
    {
        "todo": null,
        "sentence_no": null,
        "begin": "20",
        "end": "20",
        "highlightText": "files",
        "replacements": [],
        "impact": "advanced",
        "categoryHuman": "Closing punctuation",
        "id": 4,
        "starting_sentence": "### Read YAML files",
        "cell_number": 1
    },
    {
        "emotions": [],
        "action": "emotions",
        "starting_sentence": "### Read YAML files",
        "cell_number": 1
    },
    {
        "emotions": [],
        "action": "emotions",
        "starting_sentence": "Python doesn't have ",
        "cell_number": 1
    },
    {
        "todo": "change the spelling",
        "sentence_no": "0",
        "begin": "160",
        "end": "164",
        "highlightText": "yaml",
        "replacements": [],
        "impact": "critical",
        "categoryHuman": "Unknown words",
        "id": 8,
        "starting_sentence": "Be careful, some lib",
        "cell_number": 1
    },
    {
        "todo": "correct your spelling",
        "sentence_no": "0",
        "begin": "180",
        "end": "185",
        "highlightText": "JSONs",
        "replacements": [
            "JSON"
        ],
        "impact": "critical",
        "categoryHuman": "Misspelled words",
        "id": 7,
        "starting_sentence": "Be careful, some lib",
        "cell_number": 1
    },
    {
        "todo": null,
        "sentence_no": null,
        "begin": "164",
        "end": "166",
        "highlightText": "Like",
        "replacements": [],
        "impact": "advanced",
        "categoryHuman": "Punctuation in compound/complex sentences",
        "id": 9,
        "starting_sentence": "Be careful, some lib",
        "cell_number": 1
    },
    {
        "todo": null,
        "sentence_no": null,
        "begin": "11",
        "end": "17",
        "highlightText": ", some",
        "replacements": [],
        "impact": "advanced",
        "categoryHuman": "Punctuation in compound/complex sentences",
        "id": 10,
        "starting_sentence": "Be careful, some lib",
        "cell_number": 1
    },
    {
        "todo": null,
        "sentence_no": null,
        "begin": "61",
        "end": "74",
        "highlightText": "are published",
        "replacements": [],
        "impact": "advanced",
        "categoryHuman": "Passive voice misuse",
        "id": 11,
        "starting_sentence": "Be careful, some lib",
        "cell_number": 1
    },
    {
        "emotions": [
            {
                "emoji": "\ud83e\udd70",
                "emojiId": "1f970",
                "name": "loving",
                "confidence": 0.423828125
            }
        ],
        "action": "emotions",
        "starting_sentence": "Be careful, some lib",
        "cell_number": 1
    },
    {
        "todo": null,
        "sentence_no": null,
        "begin": "82",
        "end": "82",
        "highlightText": "out",
        "replacements": [],
        "impact": "advanced",
        "categoryHuman": "Closing punctuation",
        "id": 8,
        "starting_sentence": "Observe that, same a",
        "cell_number": 1
    },
    {
        "todo": null,
        "sentence_no": null,
        "begin": "38",
        "end": "42",
        "highlightText": ", we",
        "replacements": [],
        "impact": "advanced",
        "categoryHuman": "Punctuation in compound/complex sentences",
        "id": 9,
        "starting_sentence": "Observe that, same a",
        "cell_number": 1
    },
    {
        "todo": "correct your spelling",
        "sentence_no": "0",
        "begin": "79",
        "end": "83",
        "highlightText": "out'",
        "replacements": [
            "out"
        ],
        "impact": "critical",
        "categoryHuman": "Confused words",
        "id": 7,
        "starting_sentence": "Observe that, same a",
        "cell_number": 1
    },
    {
        "emotions": [],
        "action": "emotions",
        "starting_sentence": "Observe that, same a",
        "cell_number": 1
    },
    {
        "todo": null,
        "sentence_no": null,
        "begin": "187",
        "end": "189",
        "highlightText": "So",
        "replacements": [],
        "impact": "advanced",
        "categoryHuman": "Punctuation in compound/complex sentences",
        "id": 9,
        "starting_sentence": "Notice that we have ",
        "cell_number": 1
    },
    {
        "todo": null,
        "sentence_no": null,
        "begin": "248",
        "end": "254",
        "highlightText": "and/or",
        "replacements": [],
        "impact": "advanced",
        "categoryHuman": "Inappropriate colloquialisms",
        "id": 10,
        "starting_sentence": "Notice that we have ",
        "cell_number": 1
    },
    {
        "todo": "change the form of\u00a0the verb",
        "sentence_no": "0",
        "begin": "255",
        "end": "260",
        "highlightText": "index",
        "replacements": [
            "indexing"
        ],
        "impact": "critical",
        "categoryHuman": "Incorrect verb forms",
        "id": 7,
        "starting_sentence": "Notice that we have ",
        "cell_number": 1
    },
    {
        "todo": null,
        "sentence_no": null,
        "begin": "260",
        "end": "260",
        "highlightText": "index",
        "replacements": [],
        "impact": "advanced",
        "categoryHuman": "Closing punctuation",
        "id": 8,
        "starting_sentence": "Notice that we have ",
        "cell_number": 1
    },
    {
        "todo": null,
        "sentence_no": null,
        "begin": "44",
        "end": "45",
        "highlightText": "',",
        "replacements": [],
        "impact": "advanced",
        "categoryHuman": "Punctuation in compound/complex sentences",
        "id": 11,
        "starting_sentence": "Notice that we have ",
        "cell_number": 1
    },
    {
        "emotions": [
            {
                "emoji": "\u261d\ufe0f",
                "emojiId": "261d",
                "name": "assertive",
                "confidence": 0.6982421875
            }
        ],
        "action": "emotions",
        "starting_sentence": "Notice that we have ",
        "cell_number": 1
    },
    {
        "todo": null,
        "sentence_no": null,
        "begin": "22",
        "end": "22",
        "highlightText": "files",
        "replacements": [],
        "impact": "advanced",
        "categoryHuman": "Closing punctuation",
        "id": 4,
        "starting_sentence": "### Create YAML file",
        "cell_number": 1
    },
    {
        "emotions": [],
        "action": "emotions",
        "starting_sentence": "### Create YAML file",
        "cell_number": 1
    },
    {
        "todo": null,
        "sentence_no": null,
        "begin": "181",
        "end": "182",
        "highlightText": "have,",
        "replacements": [],
        "impact": "advanced",
        "categoryHuman": "Punctuation in compound/complex sentences",
        "id": 11,
        "starting_sentence": "You can also create ",
        "cell_number": 1
    },
    {
        "todo": null,
        "sentence_no": null,
        "begin": "216",
        "end": "216",
        "highlightText": "there",
        "replacements": [],
        "impact": "advanced",
        "categoryHuman": "Closing punctuation",
        "id": 10,
        "starting_sentence": "You can also create ",
        "cell_number": 1
    },
    {
        "todo": "correct your spelling",
        "sentence_no": "0",
        "begin": "211",
        "end": "217",
        "highlightText": "there'",
        "replacements": [
            "there"
        ],
        "impact": "critical",
        "categoryHuman": "Confused words",
        "id": 9,
        "starting_sentence": "You can also create ",
        "cell_number": 1
    },
    {
        "emotions": [
            {
                "emoji": "\ud83e\udd13",
                "emojiId": "1f913",
                "name": "informative",
                "confidence": 0.9970703125
            }
        ],
        "action": "emotions",
        "starting_sentence": "You can also create ",
        "cell_number": 1
    },
    {
        "todo": null,
        "sentence_no": null,
        "begin": "119",
        "end": "120",
        "highlightText": "use,",
        "replacements": [],
        "impact": "advanced",
        "categoryHuman": "Punctuation in compound/complex sentences",
        "id": 8,
        "starting_sentence": "Now, we can use the ",
        "cell_number": 1
    },
    {
        "todo": null,
        "sentence_no": null,
        "begin": "172",
        "end": "172",
        "highlightText": "data",
        "replacements": [],
        "impact": "advanced",
        "categoryHuman": "Closing punctuation",
        "id": 7,
        "starting_sentence": "Now, we can use the ",
        "cell_number": 1
    },
    {
        "todo": "change the spelling",
        "sentence_no": "0",
        "begin": "61",
        "end": "65",
        "highlightText": "yaml",
        "replacements": [],
        "impact": "critical",
        "categoryHuman": "Unknown words",
        "id": 9,
        "starting_sentence": "Now, we can use the ",
        "cell_number": 1
    },
    {
        "emotions": [
            {
                "emoji": "\u261d\ufe0f",
                "emojiId": "261d",
                "name": "assertive",
                "confidence": 0.98828125
            },
            {
                "emoji": "\ud83d\udc54",
                "emojiId": "1f454",
                "name": "formal",
                "confidence": 0.7827148438
            }
        ],
        "action": "emotions",
        "starting_sentence": "Now, we can use the ",
        "cell_number": 1
    },
    {
        "todo": "correct article usage",
        "sentence_no": "0",
        "begin": "63",
        "end": "63",
        "highlightText": "industry",
        "replacements": [
            "the "
        ],
        "impact": "critical",
        "categoryHuman": "Determiner use (a/an/the/this, etc.)",
        "id": 11,
        "starting_sentence": "# Key Takeaways  - S",
        "cell_number": 1
    },
    {
        "todo": null,
        "sentence_no": null,
        "begin": "194",
        "end": "214",
        "highlightText": "above-mentioned file",
        "replacements": [],
        "impact": "advanced",
        "categoryHuman": "Outdated language",
        "id": 12,
        "starting_sentence": "# Key Takeaways  - S",
        "cell_number": 1
    },
    {
        "todo": null,
        "sentence_no": null,
        "begin": "451",
        "end": "475",
        "highlightText": "is easily read by humans",
        "replacements": [],
        "impact": "advanced",
        "categoryHuman": "Passive voice misuse",
        "id": 13,
        "starting_sentence": "# Key Takeaways  - S",
        "cell_number": 1
    },
    {
        "todo": null,
        "sentence_no": null,
        "begin": "477",
        "end": "493",
        "highlightText": "It's widely used",
        "replacements": [],
        "impact": "advanced",
        "categoryHuman": "Passive voice misuse",
        "id": 14,
        "starting_sentence": "# Key Takeaways  - S",
        "cell_number": 1
    },
    {
        "todo": "correct your spelling",
        "sentence_no": "0",
        "begin": "561",
        "end": "575",
        "highlightText": "serisalisation",
        "replacements": [
            "serialisation",
            "serialization"
        ],
        "impact": "critical",
        "categoryHuman": "Misspelled words",
        "id": 15,
        "starting_sentence": "# Key Takeaways  - S",
        "cell_number": 1
    },
    {
        "todo": null,
        "sentence_no": null,
        "begin": "585",
        "end": "594",
        "highlightText": "which is",
        "replacements": [],
        "impact": "advanced",
        "categoryHuman": "Wordy sentences",
        "id": 16,
        "starting_sentence": "# Key Takeaways  - S",
        "cell_number": 1
    },
    {
        "emotions": [
            {
                "emoji": "\ud83e\udd1d",
                "emojiId": "1f91d",
                "name": "confident",
                "confidence": 0.9990234375
            },
            {
                "emoji": "\ud83c\udfaf",
                "emojiId": "1f3af",
                "name": "direct",
                "confidence": 0.994140625
            }
        ],
        "action": "emotions",
        "starting_sentence": "# Key Takeaways  - S",
        "cell_number": 1
    },
    {
        "num_of_corrections": 156
    }
]